rtl/control.v
`timescale 1ns / 1ps

module control (
    input  wire [7:0] instr,
    output reg  reg_write,
    output reg  alu_src,
    output reg  [2:0] alu_op,
    output reg  jump,
    output reg  branch_z,
    output reg  halt
);

    wire [3:0] opcode = instr[7:4];

    always @(*) begin
        reg_write = 0;
        alu_src = 0;
        alu_op = 3'b000;
        jump = 0;
        branch_z = 0;
        halt = 0;

        case (opcode)
            4'b0001: begin // LDI
                reg_write = 1;
                alu_src = 1;
                alu_op = 3'b000;
            end
            4'b0010: begin // ADD
                reg_write = 1;
                alu_op = 3'b000;
            end
            4'b0011: begin // SUB
                reg_write = 1;
                alu_op = 3'b001;
            end
            4'b0100: jump = 1;         // JMP
            4'b0101: branch_z = 1;     // BRZ
            4'b1111: halt = 1;         // HALT
            default: ;                 // NOP
        endcase
    end

endmodule

rtl/alu.v
`timescale 1ns / 1ps

module alu (
    input  wire [7:0] a,
    input  wire [7:0] b,
    input  wire [2:0] alu_op,
    output reg  [7:0] result,
    output wire       zero
);

    always @(*) begin
        case (alu_op)
            3'b000: result = a + b;    // ADD
            3'b001: result = a - b;    // SUB
            3'b010: result = a & b;    // AND
            3'b011: result = a | b;    // OR
            3'b100: result = ~a;       // NOT
            3'b101: result = (a < b) ? 8'd1 : 8'd0; // SLT
            default: result = 8'd0;
        endcase
    end

    assign zero = (result == 8'd0);

endmodule

rtl/registerfile.v
`timescale 1ns / 1ps

module register_file (
    input  wire clk,
    input  wire reset,
    input  wire write_enable,
    input  wire [1:0] write_addr,
    input  wire [7:0] write_data,
    input  wire [1:0] read_addr1,
    input  wire [1:0] read_addr2,
    output reg  [7:0] read_data1,
    output reg  [7:0] read_data2
);

    reg [7:0] registers [0:3];

    integer i;
    always @(posedge clk or posedge reset) begin
        if (reset) begin
            for (i = 0; i < 4; i = i + 1)
                registers[i] <= 0;
        end else if (write_enable) begin
            registers[write_addr] <= write_data;
        end
    end

    always @(*) begin
        read_data1 = registers[read_addr1];
        read_data2 = registers[read_addr2];
    end

endmodule

rtl/memory.v
`timescale 1ns / 1ps

module memory (
    input  wire [7:0] addr,
    output reg  [7:0] data_out
);

    reg [7:0] mem [0:255];

    initial begin
        mem[0] = 8'b00010001; // LDI R0, 1
        mem[1] = 8'b00010101; // LDI R1, 5
        mem[2] = 8'b00100001; // ADD R0, R1
        mem[3] = 8'b11110000; // HALT
    end

    /*initial begin
        mem[0] = 8'b00010010; // LDI R0, 2
        mem[1] = 8'b00010100; // LDI R1, 4
        mem[2] = 8'b00100001; // ADD R0, R1 -> R0 = 6
        mem[3] = 8'b00110001; // SUB R0, R1 -> R0 = 2
        mem[4] = 8'b01000001; // AND R0, R1 -> R0 = 0
        mem[5] = 8'b01010001; // OR R0, R1 -> R0 = 4
        mem[6] = 8'b01010111; // BRZ to 7 (should not branch because R0 ≠ 0)
        mem[7] = 8'b00011011; // LDI R2, 3
        mem[8] = 8'b01000100; // JMP to 4 (loop or test jump)
        mem[9] = 8'b11110000; // HALT (unreachable in this case)
    end*/

    always @(*) begin
        data_out = mem[addr];
    end

endmodule

rtl/datapath.v
`timescale 1ns / 1ps

module datapath (
    input  wire clk,
    input  wire reset,
    input  wire reg_write,
    input  wire alu_src,
    input  wire [2:0] alu_op,
    input  wire jump,
    input  wire branch_z,
    input  wire halt,
    output wire [7:0] instr,
    output wire [7:0] result_out,
    output reg  [7:0] pc
);

    wire [7:0] read1, read2, alu_b, alu_result;
    wire zero_flag;

    memory u_mem (
        .addr(pc),
        .data_out(instr)
    );

    register_file u_reg (
        .clk(clk),
        .reset(reset),
        .write_enable(reg_write),
        .write_addr(instr[3:2]),
        .write_data(alu_result),
        .read_addr1(instr[3:2]),
        .read_addr2(instr[1:0]),
        .read_data1(read1),
        .read_data2(read2)
    );

    alu u_alu (
        .a(read1),
        .b(alu_b),
        .alu_op(alu_op),
        .result(alu_result),
        .zero(zero_flag)
    );

    assign alu_b = alu_src ? {4'b0000, instr[3:0]} : read2;
    assign result_out = alu_result;

    always @(posedge clk or posedge reset) begin
        if (reset)
            pc <= 0;
        else if (halt)
            pc <= pc; // freeze PC
        else if (jump)
            pc <= {4'b0000, instr[3:0]};
        else if (branch_z && zero_flag)
            pc <= {4'b0000, instr[3:0]};
        else
            pc <= pc + 1;
    end

endmodule

rtl/top.v
module top (
    input  wire clk,
    input  wire reset,
    output wire [3:0] led_out
);

    wire [7:0] instr;
    wire [7:0] result_out;
    wire reg_write, alu_src, jump, branch_z, halt;
    wire [2:0] alu_op;
    wire [7:0] pc_debug;

    datapath u_datapath (
        .clk(clk),
        .reset(reset),
        .reg_write(reg_write),
        .alu_src(alu_src),
        .alu_op(alu_op),
        .jump(jump),
        .branch_z(branch_z),
        .halt(halt),
        .instr(instr),
        .result_out(result_out),
        .pc(pc_debug)
    );

    control u_control (
        .instr(instr),
        .reg_write(reg_write),
        .alu_src(alu_src),
        .alu_op(alu_op),
        .jump(jump),
        .branch_z(branch_z),
        .halt(halt)
    );

    //assign led_out = result_out[3:0];
    assign led_out = halt ? 4'b0000 : result_out[3:0];


endmodule

sim/top_tb.v
`timescale 1ns / 1ps

module top_tb;

    reg clk = 0;
    reg reset = 1;
    wire [3:0] led_out;

    top uut (
        .clk(clk),
        .reset(reset),
        .led_out(led_out)
    );

    always #10 clk = ~clk;

    initial begin
        $dumpfile("cpu_waveform.vcd");
        $dumpvars(0, top_tb);

        #100 reset = 0;
        #1000;

        $finish;
    end

    always @(posedge clk) begin
        //$display("PC=%h | Instr=%b | LEDs=%b", uut.u_datapath.pc, uut.u_datapath.instr, led_out);
        $display("PC=%h | Instr=%b | LEDs=%b | Z=%b N=%b C=%b", uut.u_datapath.pc, uut.u_datapath.instr, led_out, uut.u_datapath.z_flag, uut.u_datapath.n_flag, uut.u_datapath.c_flag);
        if (uut.halt) begin
            $display("HALT detected at PC=%h, stopping simulation.", uut.u_datapath.pc);
            $finish;
        end
    end


endmodule

modelsim/cpu_waveform.vcd
$date
	Mon Jun 23 22:52:57 2025
$end
$version
	ModelSim Version 2020.1
$end
$timescale
	1ps
$end

$scope module top_tb $end
$var reg 1 ! clk $end
$var reg 1 " reset $end
$var wire 1 # led_out [3] $end
$var wire 1 $ led_out [2] $end
$var wire 1 % led_out [1] $end
$var wire 1 & led_out [0] $end

$scope module uut $end
$var wire 1 ' clk $end
$var wire 1 ( reset $end
$var wire 1 # led_out [3] $end
$var wire 1 $ led_out [2] $end
$var wire 1 % led_out [1] $end
$var wire 1 & led_out [0] $end
$var wire 1 ) instr [7] $end
$var wire 1 * instr [6] $end
$var wire 1 + instr [5] $end
$var wire 1 , instr [4] $end
$var wire 1 - instr [3] $end
$var wire 1 . instr [2] $end
$var wire 1 / instr [1] $end
$var wire 1 0 instr [0] $end
$var wire 1 1 result_out [7] $end
$var wire 1 2 result_out [6] $end
$var wire 1 3 result_out [5] $end
$var wire 1 4 result_out [4] $end
$var wire 1 5 result_out [3] $end
$var wire 1 6 result_out [2] $end
$var wire 1 7 result_out [1] $end
$var wire 1 8 result_out [0] $end
$var wire 1 9 reg_write $end
$var wire 1 : alu_src $end
$var wire 1 ; jump $end
$var wire 1 < branch_z $end
$var wire 1 = halt $end
$var wire 1 > alu_op [2] $end
$var wire 1 ? alu_op [1] $end
$var wire 1 @ alu_op [0] $end
$var wire 1 A pc_debug [7] $end
$var wire 1 B pc_debug [6] $end
$var wire 1 C pc_debug [5] $end
$var wire 1 D pc_debug [4] $end
$var wire 1 E pc_debug [3] $end
$var wire 1 F pc_debug [2] $end
$var wire 1 G pc_debug [1] $end
$var wire 1 H pc_debug [0] $end

$scope module u_datapath $end
$var wire 1 ' clk $end
$var wire 1 ( reset $end
$var wire 1 9 reg_write $end
$var wire 1 : alu_src $end
$var wire 1 > alu_op [2] $end
$var wire 1 ? alu_op [1] $end
$var wire 1 @ alu_op [0] $end
$var wire 1 ; jump $end
$var wire 1 < branch_z $end
$var wire 1 = halt $end
$var wire 1 ) instr [7] $end
$var wire 1 * instr [6] $end
$var wire 1 + instr [5] $end
$var wire 1 , instr [4] $end
$var wire 1 - instr [3] $end
$var wire 1 . instr [2] $end
$var wire 1 / instr [1] $end
$var wire 1 0 instr [0] $end
$var wire 1 1 result_out [7] $end
$var wire 1 2 result_out [6] $end
$var wire 1 3 result_out [5] $end
$var wire 1 4 result_out [4] $end
$var wire 1 5 result_out [3] $end
$var wire 1 6 result_out [2] $end
$var wire 1 7 result_out [1] $end
$var wire 1 8 result_out [0] $end
$var reg 8 I pc [7:0] $end
$var wire 1 J read1 [7] $end
$var wire 1 K read1 [6] $end
$var wire 1 L read1 [5] $end
$var wire 1 M read1 [4] $end
$var wire 1 N read1 [3] $end
$var wire 1 O read1 [2] $end
$var wire 1 P read1 [1] $end
$var wire 1 Q read1 [0] $end
$var wire 1 R read2 [7] $end
$var wire 1 S read2 [6] $end
$var wire 1 T read2 [5] $end
$var wire 1 U read2 [4] $end
$var wire 1 V read2 [3] $end
$var wire 1 W read2 [2] $end
$var wire 1 X read2 [1] $end
$var wire 1 Y read2 [0] $end
$var wire 1 Z alu_b [7] $end
$var wire 1 [ alu_b [6] $end
$var wire 1 \ alu_b [5] $end
$var wire 1 ] alu_b [4] $end
$var wire 1 ^ alu_b [3] $end
$var wire 1 _ alu_b [2] $end
$var wire 1 ` alu_b [1] $end
$var wire 1 a alu_b [0] $end
$var wire 1 b alu_result [7] $end
$var wire 1 c alu_result [6] $end
$var wire 1 d alu_result [5] $end
$var wire 1 e alu_result [4] $end
$var wire 1 f alu_result [3] $end
$var wire 1 g alu_result [2] $end
$var wire 1 h alu_result [1] $end
$var wire 1 i alu_result [0] $end
$var wire 1 j zero_flag $end

$scope module u_mem $end
$var wire 1 k addr [7] $end
$var wire 1 l addr [6] $end
$var wire 1 m addr [5] $end
$var wire 1 n addr [4] $end
$var wire 1 o addr [3] $end
$var wire 1 p addr [2] $end
$var wire 1 q addr [1] $end
$var wire 1 r addr [0] $end
$var reg 8 s data_out [7:0] $end
$upscope $end

$scope module u_reg $end
$var wire 1 ' clk $end
$var wire 1 ( reset $end
$var wire 1 9 write_enable $end
$var wire 1 - write_addr [1] $end
$var wire 1 . write_addr [0] $end
$var wire 1 b write_data [7] $end
$var wire 1 c write_data [6] $end
$var wire 1 d write_data [5] $end
$var wire 1 e write_data [4] $end
$var wire 1 f write_data [3] $end
$var wire 1 g write_data [2] $end
$var wire 1 h write_data [1] $end
$var wire 1 i write_data [0] $end
$var wire 1 - read_addr1 [1] $end
$var wire 1 . read_addr1 [0] $end
$var wire 1 / read_addr2 [1] $end
$var wire 1 0 read_addr2 [0] $end
$var reg 8 t read_data1 [7:0] $end
$var reg 8 u read_data2 [7:0] $end
$var integer 32 v i $end
$upscope $end

$scope module u_alu $end
$var wire 1 J a [7] $end
$var wire 1 K a [6] $end
$var wire 1 L a [5] $end
$var wire 1 M a [4] $end
$var wire 1 N a [3] $end
$var wire 1 O a [2] $end
$var wire 1 P a [1] $end
$var wire 1 Q a [0] $end
$var wire 1 Z b [7] $end
$var wire 1 [ b [6] $end
$var wire 1 \ b [5] $end
$var wire 1 ] b [4] $end
$var wire 1 ^ b [3] $end
$var wire 1 _ b [2] $end
$var wire 1 ` b [1] $end
$var wire 1 a b [0] $end
$var wire 1 > alu_op [2] $end
$var wire 1 ? alu_op [1] $end
$var wire 1 @ alu_op [0] $end
$var reg 8 w result [7:0] $end
$var wire 1 j zero $end
$upscope $end
$upscope $end

$scope module u_control $end
$var wire 1 ) instr [7] $end
$var wire 1 * instr [6] $end
$var wire 1 + instr [5] $end
$var wire 1 , instr [4] $end
$var wire 1 - instr [3] $end
$var wire 1 . instr [2] $end
$var wire 1 / instr [1] $end
$var wire 1 0 instr [0] $end
$var reg 1 x reg_write $end
$var reg 1 y alu_src $end
$var reg 3 z alu_op [2:0] $end
$var reg 1 { jump $end
$var reg 1 | branch_z $end
$var reg 1 } halt $end
$var wire 1 ~ opcode [3] $end
$var wire 1 !! opcode [2] $end
$var wire 1 "! opcode [1] $end
$var wire 1 #! opcode [0] $end
$upscope $end
$upscope $end
$upscope $end
$enddefinitions $end
#0
$dumpvars
0!
1"
b0 I
b10010 s
b0 t
b0 u
b10 w
1x
1y
b0 z
0{
0|
0}
b100 v
0&
1%
0$
0#
00
1/
0.
0-
1,
0+
0*
0)
08
17
06
05
04
03
02
01
19
1:
0;
0<
0=
0@
0?
0>
0H
0G
0F
0E
0D
0C
0B
0A
0Q
0P
0O
0N
0M
0L
0K
0J
0Y
0X
0W
0V
0U
0T
0S
0R
0a
1`
0_
0^
0]
0\
0[
0Z
0i
1h
0g
0f
0e
0d
0c
0b
0j
1#!
0"!
0!!
0~
1(
0'
0r
0q
0p
0o
0n
0m
0l
0k
$end
#10000
1!
1'
b0 v
b1 v
b10 v
b11 v
b100 v
#20000
0!
0'
#30000
1!
1'
b0 v
b1 v
b10 v
b11 v
b100 v
#40000
0!
0'
#50000
1!
1'
b0 v
b1 v
b10 v
b11 v
b100 v
#60000
0!
0'
#70000
1!
1'
b0 v
b1 v
b10 v
b11 v
b100 v
#80000
0!
0'
#90000
1!
1'
b0 v
b1 v
b10 v
b11 v
b100 v
#100000
0"
0!
0(
0'
#110000
1!
1'
b1 I
1H
1r
b10100 s
b10 t
1P
0/
1.
0`
1_
b0 t
b10 u
b110 w
1g
1X
16
1$
0P
b100 w
0h
07
0%
#120000
0!
0'
#130000
1!
1'
b10 I
0H
1G
0r
1q
b100001 s
b100 t
1O
10
0.
0,
1+
0#!
1"!
1a
0_
0x
0y
1x
b10 t
b100 u
b101 w
0:
1i
0X
1W
18
1&
0a
1_
1P
0O
b110 w
0i
1h
08
17
0&
1%
#140000
0!
0'
#150000
1!
1'
b11 I
1H
1r
b110001 s
b110 t
1O
1,
1#!
0x
1x
b1 z
b1010 w
0g
1f
06
15
0$
1#
1@
b10 w
0f
05
0#
#160000
0!
0'
#170000
1!
1'
b100 I
0H
0G
1F
0r
0q
1p
b1000001 s
b10 t
0O
0,
0+
1*
0#!
0"!
1!!
0x
b0 z
1{
b11111110 w
09
1;
1g
1f
1e
1d
1c
1b
16
15
14
13
12
11
1$
1#
0@
b110 w
0f
0e
0d
0c
0b
05
04
03
02
01
0#
#180000
0!
0'
#190000
1!
1'
b1 I
1H
0F
1r
0p
b10100 s
00
1.
1,
0*
1#!
0!!
0{
1x
1y
b100 t
b10 u
0;
19
1:
1X
0W
0P
1O
b1000 w
0h
0g
1f
07
06
15
0%
0$
1#
#200000
0!
0'
#210000
1!
1'
b10 I
0H
1G
0r
1q
b100001 s
b1000 t
0O
1N
10
0.
0,
1+
0#!
1"!
1a
0_
0x
0y
1x
b10 t
b1000 u
b1001 w
0:
1i
0X
1V
18
1&
0a
1^
1P
0N
b1010 w
0i
1h
08
17
0&
1%
#220000
0!
0'
#230000
1!
1'
b11 I
1H
1r
b110001 s
b1010 t
1N
1,
1#!
0x
1x
b1 z
b10010 w
0f
1e
05
14
0#
1@
b10 w
0e
04
#240000
0!
0'
#250000
1!
1'
b100 I
0H
0G
1F
0r
0q
1p
b1000001 s
b10 t
0N
0,
0+
1*
0#!
0"!
1!!
0x
b0 z
1{
b11111010 w
09
1;
1f
1e
1d
1c
1b
15
14
13
12
11
1#
0@
b1010 w
0e
0d
0c
0b
04
03
02
01
#260000
0!
0'
#270000
1!
1'
b1 I
1H
0F
1r
0p
b10100 s
00
1.
1,
0*
1#!
0!!
0{
1x
1y
b1000 t
b10 u
0;
19
1:
1X
0V
1_
0^
0P
1N
b1100 w
0h
1g
07
16
0%
1$
#280000
0!
0'
#290000
1!
1'
b10 I
0H
1G
0r
1q
b100001 s
b1100 t
1O
10
0.
0,
1+
0#!
1"!
1a
0_
0x
0y
1x
b10 t
b1100 u
b1101 w
0:
1i
0X
1W
1V
18
1&
0a
1_
1^
1P
0O
0N
b1110 w
0i
1h
08
17
0&
1%
#300000
0!
0'
#310000
1!
1'
b11 I
1H
1r
b110001 s
b1110 t
1O
1N
1,
1#!
0x
1x
b1 z
b11010 w
0g
1e
06
14
0$
1@
b10 w
0f
0e
05
04
0#
#320000
0!
0'
#330000
1!
1'
b100 I
0H
0G
1F
0r
0q
1p
b1000001 s
b10 t
0O
0N
0,
0+
1*
0#!
0"!
1!!
0x
b0 z
1{
b11110110 w
09
1;
1g
1e
1d
1c
1b
16
14
13
12
11
1$
0@
b1110 w
1f
0e
0d
0c
0b
15
04
03
02
01
1#
#340000
0!
0'
#350000
1!
1'
b1 I
1H
0F
1r
0p
b10100 s
00
1.
1,
0*
1#!
0!!
0{
1x
1y
b1100 t
b10 u
0;
19
1:
1X
0W
0V
0^
0P
1O
1N
b10000 w
0h
0g
0f
1e
07
06
05
14
0%
0$
0#
#360000
0!
0'
#370000
1!
1'
b10 I
0H
1G
0r
1q
b100001 s
b10000 t
0O
0N
1M
10
0.
0,
1+
0#!
1"!
1a
0_
0x
0y
1x
b10 t
b10000 u
b10001 w
0:
1i
0X
1U
18
1&
0a
1]
1P
0M
b10010 w
0i
1h
08
17
0&
1%
#380000
0!
0'
#390000
1!
1'
b11 I
1H
1r
b110001 s
b10010 t
1M
1,
1#!
0x
1x
b1 z
b100010 w
0e
1d
04
13
1@
b10 w
0d
03
#400000
0!
0'
#410000
1!
1'
b100 I
0H
0G
1F
0r
0q
1p
b1000001 s
b10 t
0M
0,
0+
1*
0#!
0"!
1!!
0x
b0 z
1{
b11110010 w
09
1;
1e
1d
1c
1b
14
13
12
11
0@
b10010 w
0d
0c
0b
03
02
01
#420000
0!
0'
#430000
1!
1'
b1 I
1H
0F
1r
0p
b10100 s
00
1.
1,
0*
1#!
0!!
0{
1x
1y
b10000 t
b10 u
0;
19
1:
1X
0U
1_
0]
0P
1M
b10100 w
0h
1g
07
16
0%
1$
#440000
0!
0'
#450000
1!
1'
b10 I
0H
1G
0r
1q
b100001 s
b10100 t
1O
10
0.
0,
1+
0#!
1"!
1a
0_
0x
0y
1x
b10 t
b10100 u
b10101 w
0:
1i
0X
1W
1U
18
1&
0a
1_
1]
1P
0O
0M
b10110 w
0i
1h
08
17
0&
1%
#460000
0!
0'
#470000
1!
1'
b11 I
1H
1r
b110001 s
b10110 t
1O
1M
1,
1#!
0x
1x
b1 z
b101010 w
0g
1f
0e
1d
06
15
04
13
0$
1#
1@
b10 w
0f
0d
05
03
0#
#480000
0!
0'
#490000
1!
1'
b100 I
0H
0G
1F
0r
0q
1p
b1000001 s
b10 t
0O
0M
0,
0+
1*
0#!
0"!
1!!
0x
b0 z
1{
b11101110 w
09
1;
1g
1f
1d
1c
1b
16
15
13
12
11
1$
1#
0@
b10110 w
0f
1e
0d
0c
0b
05
14
03
02
01
0#
#500000
0!
0'
#510000
1!
1'
b1 I
1H
0F
1r
0p
b10100 s
00
1.
1,
0*
1#!
0!!
0{
1x
1y
b10100 t
b10 u
0;
19
1:
1X
0W
0U
0]
0P
1O
1M
b11000 w
0h
0g
1f
07
06
15
0%
0$
1#
#520000
0!
0'
#530000
1!
1'
b10 I
0H
1G
0r
1q
b100001 s
b11000 t
0O
1N
10
0.
0,
1+
0#!
1"!
1a
0_
0x
0y
1x
b10 t
b11000 u
b11001 w
0:
1i
0X
1V
1U
18
1&
0a
1^
1]
1P
0N
0M
b11010 w
0i
1h
08
17
0&
1%
#540000
0!
0'
#550000
1!
1'
b11 I
1H
1r
b110001 s
b11010 t
1N
1M
1,
1#!
0x
1x
b1 z
b110010 w
0f
1d
05
13
0#
1@
b10 w
0e
0d
04
03
#560000
0!
0'
#570000
1!
1'
b100 I
0H
0G
1F
0r
0q
1p
b1000001 s
b10 t
0N
0M
0,
0+
1*
0#!
0"!
1!!
0x
b0 z
1{
b11101010 w
09
1;
1f
1d
1c
1b
15
13
12
11
1#
0@
b11010 w
1e
0d
0c
0b
14
03
02
01
#580000
0!
0'
#590000
1!
1'
b1 I
1H
0F
1r
0p
b10100 s
00
1.
1,
0*
1#!
0!!
0{
1x
1y
b11000 t
b10 u
0;
19
1:
1X
0V
0U
1_
0^
0]
0P
1N
1M
b11100 w
0h
1g
07
16
0%
1$
#600000
0!
0'
#610000
1!
1'
b10 I
0H
1G
0r
1q
b100001 s
b11100 t
1O
10
0.
0,
1+
0#!
1"!
1a
0_
0x
0y
1x
b10 t
b11100 u
b11101 w
0:
1i
0X
1W
1V
1U
18
1&
0a
1_
1^
1]
1P
0O
0N
0M
b11110 w
0i
1h
08
17
0&
1%
#620000
0!
0'
#630000
1!
1'
b11 I
1H
1r
b110001 s
b11110 t
1O
1N
1M
1,
1#!
0x
1x
b1 z
b111010 w
0g
1d
06
13
0$
1@
b10 w
0f
0e
0d
05
04
03
0#
#640000
0!
0'
#650000
1!
1'
b100 I
0H
0G
1F
0r
0q
1p
b1000001 s
b10 t
0O
0N
0M
0,
0+
1*
0#!
0"!
1!!
0x
b0 z
1{
b11100110 w
09
1;
1g
1d
1c
1b
16
13
12
11
1$
0@
b11110 w
1f
1e
0d
0c
0b
15
14
03
02
01
1#
#660000
0!
0'
#670000
1!
1'
b1 I
1H
0F
1r
0p
b10100 s
00
1.
1,
0*
1#!
0!!
0{
1x
1y
b11100 t
b10 u
0;
19
1:
1X
0W
0V
0U
0^
0]
0P
1O
1N
1M
b100000 w
0h
0g
0f
0e
1d
07
06
05
04
13
0%
0$
0#
#680000
0!
0'
#690000
1!
1'
b10 I
0H
1G
0r
1q
b100001 s
b100000 t
0O
0N
0M
1L
10
0.
0,
1+
0#!
1"!
1a
0_
0x
0y
1x
b10 t
b100000 u
b100001 w
0:
1i
0X
1T
18
1&
0a
1\
1P
0L
b100010 w
0i
1h
08
17
0&
1%
#700000
0!
0'
#710000
1!
1'
b11 I
1H
1r
b110001 s
b100010 t
1L
1,
1#!
0x
1x
b1 z
b1000010 w
0d
1c
03
12
1@
b10 w
0c
02
#720000
0!
0'
#730000
1!
1'
b100 I
0H
0G
1F
0r
0q
1p
b1000001 s
b10 t
0L
0,
0+
1*
0#!
0"!
1!!
0x
b0 z
1{
b11100010 w
09
1;
1d
1c
1b
13
12
11
0@
b100010 w
0c
0b
02
01
#740000
0!
0'
#750000
1!
1'
b1 I
1H
0F
1r
0p
b10100 s
00
1.
1,
0*
1#!
0!!
0{
1x
1y
b100000 t
b10 u
0;
19
1:
1X
0T
1_
0\
0P
1L
b100100 w
0h
1g
07
16
0%
1$
#760000
0!
0'
#770000
1!
1'
b10 I
0H
1G
0r
1q
b100001 s
b100100 t
1O
10
0.
0,
1+
0#!
1"!
1a
0_
0x
0y
1x
b10 t
b100100 u
b100101 w
0:
1i
0X
1W
1T
18
1&
0a
1_
1\
1P
0O
0L
b100110 w
0i
1h
08
17
0&
1%
#780000
0!
0'
#790000
1!
1'
b11 I
1H
1r
b110001 s
b100110 t
1O
1L
1,
1#!
0x
1x
b1 z
b1001010 w
0g
1f
0d
1c
06
15
03
12
0$
1#
1@
b10 w
0f
0c
05
02
0#
#800000
0!
0'
#810000
1!
1'
b100 I
0H
0G
1F
0r
0q
1p
b1000001 s
b10 t
0O
0L
0,
0+
1*
0#!
0"!
1!!
0x
b0 z
1{
b11011110 w
09
1;
1g
1f
1e
1c
1b
16
15
14
12
11
1$
1#
0@
b100110 w
0f
0e
1d
0c
0b
05
04
13
02
01
0#
#820000
0!
0'
#830000
1!
1'
b1 I
1H
0F
1r
0p
b10100 s
00
1.
1,
0*
1#!
0!!
0{
1x
1y
b100100 t
b10 u
0;
19
1:
1X
0W
0T
0\
0P
1O
1L
b101000 w
0h
