rtl/control.v
`timescale 1ns / 1ps

module control (
    input  wire [7:0] instr,
    output reg  reg_write,
    output reg  alu_src,
    output reg  [2:0] alu_op,
    output reg  jump,
    output reg  branch_z,
    output reg  halt
);

    wire [3:0] opcode = instr[7:4];

    always @(*) begin
        reg_write = 0;
        alu_src = 0;
        alu_op = 3'b000;
        jump = 0;
        branch_z = 0;
        halt = 0;

        case (opcode)
            4'b0001: begin // LDI
                reg_write = 1;
                alu_src = 1;
                alu_op = 3'b000;
            end
            4'b0010: begin // ADD
                reg_write = 1;
                alu_op = 3'b000;
            end
            4'b0011: begin // SUB
                reg_write = 1;
                alu_op = 3'b001;
            end
            4'b0100: jump = 1;         // JMP
            4'b0101: branch_z = 1;     // BRZ
            4'b1111: halt = 1;         // HALT
            default: ;                 // NOP
        endcase
    end

endmodule

rtl/alu.v
`timescale 1ns / 1ps

module alu (
    input  wire [7:0] a,
    input  wire [7:0] b,
    input  wire [2:0] alu_op,
    output reg  [7:0] result,
    output wire       zero
);

    always @(*) begin
        case (alu_op)
            3'b000: result = a + b;    // ADD
            3'b001: result = a - b;    // SUB
            3'b010: result = a & b;    // AND
            3'b011: result = a | b;    // OR
            3'b100: result = ~a;       // NOT
            3'b101: result = (a < b) ? 8'd1 : 8'd0; // SLT
            default: result = 8'd0;
        endcase
    end

    assign zero = (result == 8'd0);

endmodule

rtl/registerfile.v
`timescale 1ns / 1ps

module register_file (
    input  wire clk,
    input  wire reset,
    input  wire write_enable,
    input  wire [1:0] write_addr,
    input  wire [7:0] write_data,
    input  wire [1:0] read_addr1,
    input  wire [1:0] read_addr2,
    output reg  [7:0] read_data1,
    output reg  [7:0] read_data2
);

    reg [7:0] registers [0:3];

    integer i;
    always @(posedge clk or posedge reset) begin
        if (reset) begin
            for (i = 0; i < 4; i = i + 1)
                registers[i] <= 0;
        end else if (write_enable) begin
            registers[write_addr] <= write_data;
        end
    end

    always @(*) begin
        read_data1 = registers[read_addr1];
        read_data2 = registers[read_addr2];
    end

endmodule

rtl/memory.v
`timescale 1ns / 1ps

module memory (
    input  wire [7:0] addr,
    output reg  [7:0] data_out
);

    reg [7:0] mem [0:255];

    initial begin
        mem[0] = 8'b00010001; // LDI R0, 1
        mem[1] = 8'b00010101; // LDI R1, 5
        mem[2] = 8'b00100001; // ADD R0, R1
        mem[3] = 8'b11110000; // HALT
    end

    /*initial begin
        mem[0] = 8'b00010010; // LDI R0, 2
        mem[1] = 8'b00010100; // LDI R1, 4
        mem[2] = 8'b00100001; // ADD R0, R1 -> R0 = 6
        mem[3] = 8'b00110001; // SUB R0, R1 -> R0 = 2
        mem[4] = 8'b01000001; // AND R0, R1 -> R0 = 0
        mem[5] = 8'b01010001; // OR R0, R1 -> R0 = 4
        mem[6] = 8'b01010111; // BRZ to 7 (should not branch because R0 ≠ 0)
        mem[7] = 8'b00011011; // LDI R2, 3
        mem[8] = 8'b01000100; // JMP to 4 (loop or test jump)
        mem[9] = 8'b11110000; // HALT (unreachable in this case)
    end*/

    always @(*) begin
        data_out = mem[addr];
    end

endmodule

rtl/datapath.v
`timescale 1ns / 1ps

module datapath (
    input  wire clk,
    input  wire reset,
    input  wire reg_write,
    input  wire alu_src,
    input  wire [2:0] alu_op,
    input  wire jump,
    input  wire branch_z,
    input  wire halt,
    output wire [7:0] instr,
    output wire [7:0] result_out,
    output reg  [7:0] pc
);

    wire [7:0] read1, read2, alu_b, alu_result;
    wire zero_flag;

    memory u_mem (
        .addr(pc),
        .data_out(instr)
    );

    register_file u_reg (
        .clk(clk),
        .reset(reset),
        .write_enable(reg_write),
        .write_addr(instr[3:2]),
        .write_data(alu_result),
        .read_addr1(instr[3:2]),
        .read_addr2(instr[1:0]),
        .read_data1(read1),
        .read_data2(read2)
    );

    alu u_alu (
        .a(read1),
        .b(alu_b),
        .alu_op(alu_op),
        .result(alu_result),
        .zero(zero_flag)
    );

    assign alu_b = alu_src ? {4'b0000, instr[3:0]} : read2;
    assign result_out = alu_result;

    always @(posedge clk or posedge reset) begin
        if (reset)
            pc <= 0;
        else if (halt)
            pc <= pc; // freeze PC
        else if (jump)
            pc <= {4'b0000, instr[3:0]};
        else if (branch_z && zero_flag)
            pc <= {4'b0000, instr[3:0]};
        else
            pc <= pc + 1;
    end

endmodule

rtl/top.v
module top (
    input  wire clk,
    input  wire reset,
    output wire [3:0] led_out
);

    wire [7:0] instr;
    wire [7:0] result_out;
    wire reg_write, alu_src, jump, branch_z, halt;
    wire [2:0] alu_op;
    wire [7:0] pc_debug;

    datapath u_datapath (
        .clk(clk),
        .reset(reset),
        .reg_write(reg_write),
        .alu_src(alu_src),
        .alu_op(alu_op),
        .jump(jump),
        .branch_z(branch_z),
        .halt(halt),
        .instr(instr),
        .result_out(result_out),
        .pc(pc_debug)
    );

    control u_control (
        .instr(instr),
        .reg_write(reg_write),
        .alu_src(alu_src),
        .alu_op(alu_op),
        .jump(jump),
        .branch_z(branch_z),
        .halt(halt)
    );

    //assign led_out = result_out[3:0];
    assign led_out = halt ? 4'b0000 : result_out[3:0];


endmodule

sim/top_tb.v
`timescale 1ns / 1ps

module top_tb;

    reg clk = 0;
    reg reset = 1;
    wire [3:0] led_out;

    top uut (
        .clk(clk),
        .reset(reset),
        .led_out(led_out)
    );

    always #10 clk = ~clk;

    initial begin
        $dumpfile("cpu_waveform.vcd");
        $dumpvars(0, top_tb);

        #100 reset = 0;
        #1000;

        $finish;
    end

    always @(posedge clk) begin
        //$display("PC=%h | Instr=%b | LEDs=%b", uut.u_datapath.pc, uut.u_datapath.instr, led_out);
        $display("PC=%h | Instr=%b | LEDs=%b | Z=%b N=%b C=%b", uut.u_datapath.pc, uut.u_datapath.instr, led_out, uut.u_datapath.z_flag, uut.u_datapath.n_flag, uut.u_datapath.c_flag);
        if (uut.halt) begin
            $display("HALT detected at PC=%h, stopping simulation.", uut.u_datapath.pc);
            $finish;
        end
    end


endmodule

modelsim/cpu_waveform.vcd
$date
	Tue Jun 24 08:58:09 2025
$end
$version
	ModelSim Version 2020.1
$end
$timescale
	1ps
$end

$scope module top_tb $end
$var reg 1 ! clk $end
$var reg 1 " reset $end
$var wire 1 # led_out [3] $end
$var wire 1 $ led_out [2] $end
$var wire 1 % led_out [1] $end
$var wire 1 & led_out [0] $end

$scope module uut $end
$var wire 1 ' clk $end
$var wire 1 ( reset $end
$var wire 1 # led_out [3] $end
$var wire 1 $ led_out [2] $end
$var wire 1 % led_out [1] $end
$var wire 1 & led_out [0] $end
$var wire 1 ) instr [7] $end
$var wire 1 * instr [6] $end
$var wire 1 + instr [5] $end
$var wire 1 , instr [4] $end
$var wire 1 - instr [3] $end
$var wire 1 . instr [2] $end
$var wire 1 / instr [1] $end
$var wire 1 0 instr [0] $end
$var wire 1 1 result_out [7] $end
$var wire 1 2 result_out [6] $end
$var wire 1 3 result_out [5] $end
$var wire 1 4 result_out [4] $end
$var wire 1 5 result_out [3] $end
$var wire 1 6 result_out [2] $end
$var wire 1 7 result_out [1] $end
$var wire 1 8 result_out [0] $end
$var wire 1 9 reg_write $end
$var wire 1 : alu_src $end
$var wire 1 ; jump $end
$var wire 1 < branch_z $end
$var wire 1 = halt $end
$var wire 1 > alu_op [2] $end
$var wire 1 ? alu_op [1] $end
$var wire 1 @ alu_op [0] $end
$var wire 1 A pc_debug [7] $end
$var wire 1 B pc_debug [6] $end
$var wire 1 C pc_debug [5] $end
$var wire 1 D pc_debug [4] $end
$var wire 1 E pc_debug [3] $end
$var wire 1 F pc_debug [2] $end
$var wire 1 G pc_debug [1] $end
$var wire 1 H pc_debug [0] $end

$scope module u_datapath $end
$var wire 1 ' clk $end
$var wire 1 ( reset $end
$var wire 1 9 reg_write $end
$var wire 1 : alu_src $end
$var wire 1 > alu_op [2] $end
$var wire 1 ? alu_op [1] $end
$var wire 1 @ alu_op [0] $end
$var wire 1 ; jump $end
$var wire 1 < branch_z $end
$var wire 1 = halt $end
$var wire 1 ) instr [7] $end
$var wire 1 * instr [6] $end
$var wire 1 + instr [5] $end
$var wire 1 , instr [4] $end
$var wire 1 - instr [3] $end
$var wire 1 . instr [2] $end
$var wire 1 / instr [1] $end
$var wire 1 0 instr [0] $end
$var wire 1 1 result_out [7] $end
$var wire 1 2 result_out [6] $end
$var wire 1 3 result_out [5] $end
$var wire 1 4 result_out [4] $end
$var wire 1 5 result_out [3] $end
$var wire 1 6 result_out [2] $end
$var wire 1 7 result_out [1] $end
$var wire 1 8 result_out [0] $end
$var reg 8 I pc [7:0] $end
$var wire 1 J read1 [7] $end
$var wire 1 K read1 [6] $end
$var wire 1 L read1 [5] $end
$var wire 1 M read1 [4] $end
$var wire 1 N read1 [3] $end
$var wire 1 O read1 [2] $end
$var wire 1 P read1 [1] $end
$var wire 1 Q read1 [0] $end
$var wire 1 R read2 [7] $end
$var wire 1 S read2 [6] $end
$var wire 1 T read2 [5] $end
$var wire 1 U read2 [4] $end
$var wire 1 V read2 [3] $end
$var wire 1 W read2 [2] $end
$var wire 1 X read2 [1] $end
$var wire 1 Y read2 [0] $end
$var wire 1 Z alu_b [7] $end
$var wire 1 [ alu_b [6] $end
$var wire 1 \ alu_b [5] $end
$var wire 1 ] alu_b [4] $end
$var wire 1 ^ alu_b [3] $end
$var wire 1 _ alu_b [2] $end
$var wire 1 ` alu_b [1] $end
$var wire 1 a alu_b [0] $end
$var wire 1 b alu_result [7] $end
$var wire 1 c alu_result [6] $end
$var wire 1 d alu_result [5] $end
$var wire 1 e alu_result [4] $end
$var wire 1 f alu_result [3] $end
$var wire 1 g alu_result [2] $end
$var wire 1 h alu_result [1] $end
$var wire 1 i alu_result [0] $end
$var wire 1 j zero_flag $end

$scope module u_mem $end
$var wire 1 k addr [7] $end
$var wire 1 l addr [6] $end
$var wire 1 m addr [5] $end
$var wire 1 n addr [4] $end
$var wire 1 o addr [3] $end
$var wire 1 p addr [2] $end
$var wire 1 q addr [1] $end
$var wire 1 r addr [0] $end
$var reg 8 s data_out [7:0] $end
$upscope $end

$scope module u_reg $end
$var wire 1 ' clk $end
$var wire 1 ( reset $end
$var wire 1 9 write_enable $end
$var wire 1 - write_addr [1] $end
$var wire 1 . write_addr [0] $end
$var wire 1 b write_data [7] $end
$var wire 1 c write_data [6] $end
$var wire 1 d write_data [5] $end
$var wire 1 e write_data [4] $end
$var wire 1 f write_data [3] $end
$var wire 1 g write_data [2] $end
$var wire 1 h write_data [1] $end
$var wire 1 i write_data [0] $end
$var wire 1 - read_addr1 [1] $end
$var wire 1 . read_addr1 [0] $end
$var wire 1 / read_addr2 [1] $end
$var wire 1 0 read_addr2 [0] $end
$var reg 8 t read_data1 [7:0] $end
$var reg 8 u read_data2 [7:0] $end
$var integer 32 v i $end
$upscope $end

$scope module u_alu $end
$var wire 1 J a [7] $end
$var wire 1 K a [6] $end
$var wire 1 L a [5] $end
$var wire 1 M a [4] $end
$var wire 1 N a [3] $end
$var wire 1 O a [2] $end
$var wire 1 P a [1] $end
$var wire 1 Q a [0] $end
$var wire 1 Z b [7] $end
$var wire 1 [ b [6] $end
$var wire 1 \ b [5] $end
$var wire 1 ] b [4] $end
$var wire 1 ^ b [3] $end
$var wire 1 _ b [2] $end
$var wire 1 ` b [1] $end
$var wire 1 a b [0] $end
$var wire 1 > alu_op [2] $end
$var wire 1 ? alu_op [1] $end
$var wire 1 @ alu_op [0] $end
$var reg 8 w result [7:0] $end
$var wire 1 j zero $end
$upscope $end
$upscope $end

$scope module u_control $end
$var wire 1 ) instr [7] $end
$var wire 1 * instr [6] $end
$var wire 1 + instr [5] $end
$var wire 1 , instr [4] $end
$var wire 1 - instr [3] $end
$var wire 1 . instr [2] $end
$var wire 1 / instr [1] $end
$var wire 1 0 instr [0] $end
$var reg 1 x reg_write $end
$var reg 1 y alu_src $end
$var reg 3 z alu_op [2:0] $end
$var reg 1 { jump $end
$var reg 1 | branch_z $end
$var reg 1 } halt $end
$var wire 1 ~ opcode [3] $end
$var wire 1 !! opcode [2] $end
$var wire 1 "! opcode [1] $end
$var wire 1 #! opcode [0] $end
$upscope $end
$upscope $end
$upscope $end
$enddefinitions $end
#0
$dumpvars
0!
1"
b0 I
b10010 s
b0 t
b0 u
b10 w
1x
1y
b0 z
0{
0|
0}
b100 v
0&
1%
0$
0#
00
1/
0.
0-
1,
0+
0*
0)
08
17
06
05
04
03
02
01
19
1:
0;
0<
0=
0@
0?
0>
0H
0G
0F
0E
0D
0C
0B
0A
0Q
0P
0O
0N
0M
0L
0K
0J
0Y
0X
0W
0V
0U
0T
0S
0R
0a
1`
0_
0^
0]
0\
0[
0Z
0i
1h
0g
0f
0e
0d
0c
0b
0j
1#!
0"!
0!!
0~
1(
0'
0r
0q
0p
0o
0n
0m
0l
0k
$end
#10000
1!
1'
b0 v
b1 v
b10 v
b11 v
b100 v
#20000
0!
0'
#30000
1!
1'
b0 v
b1 v
b10 v
b11 v
b100 v
#40000
0!
0'
#50000
1!
1'
b0 v
b1 v
b10 v
b11 v
b100 v
#60000
0!
0'
#70000
1!
1'
b0 v
b1 v
b10 v
b11 v
b100 v
#80000
0!
0'
#90000
1!
1'
b0 v
b1 v
b10 v
b11 v
b100 v
#100000
0"
0!
0(
0'
#110000
1!
1'
b1 I
1H
1r
b10101 s
b10 t
1P
10
0/
1.
1a
0`
1_
b0 t
b111 w
1i
1g
18
16
1&
1$
0P
b101 w
0h
07
0%
#120000
0!
0'
#130000
1!
1'
b10 I
0H
1G
0r
1q
b1000001 s
b101 t
b101 u
1Y
1W
1Q
1O
0.
0,
1*
0#!
1!!
0_
0x
0y
1{
b10 t
b110 w
09
0:
1;
0i
1h
08
17
0&
1%
1_
0Q
1P
0O
b111 w
1i
18
1&
#140000
0!
0'
#150000
1!
1'
b1 I
1H
0G
1r
0q
b10101 s
1.
1,
0*
1#!
0!!
0{
1x
1y
b101 t
0;
19
1:
1Q
0P
1O
b1010 w
0i
0g
1f
08
06
15
0&
0$
1#
#160000
0!
0'
#170000
1!
1'
b10 I
0H
1G
0r
1q
b1000001 s
b1010 t
b1010 u
0Y
1X
0W
1V
0Q
1P
0O
1N
0.
0,
1*
0#!
1!!
0_
0x
0y
1{
b10 t
b1011 w
09
0:
1;
1i
18
1&
0a
1`
1^
0N
b1100 w
0i
0h
1g
08
07
16
0&
0%
1$
#180000
0!
0'
#190000
1!
1'
b1 I
1H
0G
1r
0q
b10101 s
1.
1,
0*
1#!
0!!
0{
1x
1y
b1010 t
0;
19
1:
1a
0`
1_
0^
1N
b1111 w
1i
1h
18
17
1&
1%
#200000
0!
0'
#210000
1!
1'
b10 I
0H
1G
0r
1q
b1000001 s
b1111 t
b1111 u
1Y
1W
1Q
1O
0.
0,
1*
0#!
1!!
0_
0x
0y
1{
b10 t
b10000 w
09
0:
1;
0i
0h
0g
0f
1e
08
07
06
05
14
0&
0%
0$
0#
1`
1_
1^
0Q
0O
0N
b10001 w
1i
18
1&
#220000
0!
0'
#230000
1!
1'
b1 I
1H
0G
1r
0q
b10101 s
1.
1,
0*
1#!
0!!
0{
1x
1y
b1111 t
0;
19
1:
0`
0^
1Q
1O
1N
b10100 w
0i
1g
08
16
0&
1$
#240000
0!
0'
#250000
1!
1'
b10 I
0H
1G
0r
1q
b1000001 s
b10100 t
b10100 u
0Y
0X
0V
1U
0Q
0P
0N
1M
0.
0,
1*
0#!
1!!
0_
0x
0y
1{
b10 t
b10101 w
09
0:
1;
1i
18
1&
0a
1_
1]
1P
0O
0M
b10110 w
0i
1h
08
17
0&
1%
#260000
0!
0'
#270000
1!
1'
b1 I
1H
0G
1r
0q
b10101 s
1.
1,
0*
1#!
0!!
0{
1x
1y
b10100 t
0;
19
1:
1a
0]
0P
1O
1M
b11001 w
1i
0h
0g
1f
18
07
06
15
1&
0%
0$
1#
#280000
0!
0'
#290000
1!
1'
b10 I
0H
1G
0r
1q
b1000001 s
b11001 t
b11001 u
1Y
0W
1V
1Q
0O
1N
0.
0,
1*
0#!
1!!
0_
0x
0y
1{
b10 t
b11010 w
09
0:
1;
0i
1h
08
17
0&
1%
1^
1]
0Q
1P
0N
0M
b11011 w
1i
18
1&
#300000
0!
0'
#310000
1!
1'
b1 I
1H
0G
1r
0q
b10101 s
1.
1,
0*
1#!
0!!
0{
1x
1y
b11001 t
0;
19
1:
1_
0^
0]
1Q
0P
1N
1M
b11110 w
0i
1g
08
16
0&
1$
#320000
0!
0'
#330000
1!
1'
b10 I
0H
1G
0r
1q
b1000001 s
b11110 t
b11110 u
0Y
1X
1W
0Q
1P
1O
0.
0,
1*
0#!
1!!
0_
0x
0y
1{
b10 t
b11111 w
09
0:
1;
1i
18
1&
0a
1`
1_
1^
1]
0O
0N
0M
b100000 w
0i
0h
0g
0f
0e
1d
08
07
06
05
04
13
0&
0%
0$
0#
#340000
0!
0'
#350000
1!
1'
b1 I
1H
0G
1r
0q
b10101 s
1.
1,
0*
1#!
0!!
0{
1x
1y
b11110 t
0;
19
1:
1a
0`
0^
0]
1O
1N
1M
b100011 w
1i
1h
18
17
1&
1%
#360000
0!
0'
#370000
1!
1'
b10 I
0H
1G
0r
1q
b1000001 s
b100011 t
b100011 u
1Y
0W
0V
0U
1T
1Q
0O
0N
0M
1L
0.
0,
1*
0#!
1!!
0_
0x
0y
1{
b10 t
b100100 w
09
0:
1;
0i
0h
1g
08
07
16
0&
0%
1$
1`
1\
0Q
0L
b100101 w
1i
18
1&
#380000
0!
0'
#390000
1!
1'
b1 I
1H
0G
1r
0q
b10101 s
1.
1,
0*
1#!
0!!
0{
1x
1y
b100011 t
0;
19
1:
0`
1_
0\
1Q
1L
b101000 w
0i
0g
1f
08
06
15
0&
0$
1#
#400000
0!
0'
#410000
1!
1'
b10 I
0H
1G
0r
1q
b1000001 s
b101000 t
b101000 u
0Y
0X
1V
0Q
0P
1N
0.
0,
1*
0#!
1!!
0_
0x
0y
1{
b10 t
b101001 w
09
0:
1;
1i
18
1&
0a
1^
1\
1P
0N
0L
b101010 w
0i
1h
08
17
0&
1%
#420000
0!
0'
#430000
1!
1'
b1 I
1H
0G
1r
0q
b10101 s
1.
1,
0*
1#!
0!!
0{
1x
1y
b101000 t
0;
19
1:
1a
1_
0^
0\
0P
1N
1L
b101101 w
1i
0h
1g
18
07
16
1&
0%
1$
#440000
0!
0'
#450000
1!
1'
b10 I
0H
1G
0r
1q
b1000001 s
b101101 t
b101101 u
1Y
1W
1Q
1O
0.
0,
1*
0#!
1!!
0_
0x
0y
1{
b10 t
b101110 w
09
0:
1;
0i
1h
08
17
0&
1%
1_
1^
1\
0Q
1P
0O
0N
0L
b101111 w
1i
18
1&
#460000
0!
0'
#470000
1!
1'
b1 I
1H
0G
1r
0q
b10101 s
1.
1,
0*
1#!
0!!
0{
1x
1y
b101101 t
0;
19
1:
0^
0\
1Q
0P
1O
1N
1L
b110010 w
0i
0g
0f
1e
08
06
05
14
0&
0$
0#
#480000
0!
0'
#490000
1!
1'
b10 I
0H
1G
0r
1q
b1000001 s
b110010 t
b110010 u
0Y
1X
0W
0V
1U
0Q
1P
0O
0N
1M
0.
0,
1*
0#!
1!!
0_
0x
0y
1{
b10 t
b110011 w
09
0:
1;
1i
18
1&
0a
1`
1]
1\
0M
0L
b110100 w
0i
0h
1g
08
07
16
0&
0%
1$
#500000
0!
0'
#510000
1!
1'
b1 I
1H
0G
1r
0q
b10101 s
1.
1,
0*
1#!
0!!
0{
1x
1y
b110010 t
0;
19
1:
1a
0`
1_
0]
0\
1M
1L
b110111 w
1i
1h
18
17
1&
1%
#520000
0!
0'
#530000
1!
1'
b10 I
0H
1G
0r
1q
b1000001 s
b110111 t
b110111 u
1Y
1W
1Q
1O
0.
0,
1*
0#!
1!!
0_
0x
0y
1{
b10 t
b111000 w
09
0:
1;
0i
0h
0g
1f
08
07
06
15
0&
0%
0$
1#
1`
1_
1]
1\
0Q
0O
0M
0L
b111001 w
1i
18
1&
#540000
0!
0'
#550000
1!
1'
b1 I
1H
0G
1r
0q
b10101 s
1.
1,
0*
1#!
0!!
0{
1x
1y
b110111 t
0;
19
1:
0`
0]
0\
1Q
1O
1M
1L
b111100 w
0i
1g
08
16
0&
1$
#560000
0!
0'
#570000
1!
1'
b10 I
0H
1G
0r
1q
b1000001 s
b111100 t
b111100 u
0Y
0X
1V
0Q
0P
1N
0.
0,
1*
0#!
1!!
0_
0x
0y
1{
b10 t
b111101 w
09
0:
1;
1i
18
1&
0a
1_
1^
1]
1\
1P
0O
0N
0M
0L
b111110 w
0i
1h
08
17
0&
1%
#580000
0!
0'
#590000
1!
1'
b1 I
1H
0G
1r
0q
b10101 s
1.
1,
0*
1#!
0!!
0{
1x
1y
b111100 t
0;
19
1:
1a
0^
0]
0\
0P
1O
1N
1M
1L
b1000001 w
1i
0h
0g
0f
0e
0d
1c
18
07
06
05
04
03
12
1&
0%
0$
0#
#600000
0!
0'
#610000
1!
1'
b10 I
0H
1G
0r
1q
b1000001 s
b1000001 t
b1000001 u
1Y
0W
0V
0U
0T
1S
1Q
0O
0N
0M
0L
1K
0.
0,
1*
0#!
1!!
0_
0x
0y
1{
b10 t
b1000010 w
09
0:
1;
0i
1h
08
17
0&
1%
1[
0Q
1P
0K
b1000011 w
1i
18
1&
#620000
0!
0'
#630000
1!
1'
b1 I
1H
0G
1r
0q
b10101 s
1.
1,
0*
1#!
0!!
0{
1x
1y
b1000001 t
0;
19
1:
1_
0[
1Q
0P
1K
b1000110 w
0i
1g
08
16
0&
1$
#640000
0!
0'
#650000
1!
1'
b10 I
0H
1G
0r
1q
b1000001 s
b1000110 t
b1000110 u
0Y
1X
1W
0Q
1P
1O
0.
0,
1*
0#!
1!!
0_
0x
0y
1{
b10 t
b1000111 w
09
0:
1;
1i
18
1&
0a
1`
1_
1[
0O
0K
b1001000 w
0i
0h
0g
1f
08
07
06
15
0&
0%
0$
1#
#660000
0!
0'
#670000
1!
1'
b1 I
1H
0G
1r
0q
b10101 s
1.
1,
0*
1#!
0!!
0{
1x
1y
b1000110 t
0;
19
1:
1a
0`
0[
1O
1K
b1001011 w
1i
1h
18
17
1&
1%
#680000
0!
0'
#690000
1!
1'
b10 I
0H
1G
0r
1q
b1000001 s
b1001011 t
b1001011 u
1Y
0W
1V
1Q
0O
1N
0.
0,
1*
0#!
1!!
0_
0x
0y
1{
b10 t
b1001100 w
09
0:
1;
0i
0h
1g
08
07
16
0&
0%
1$
1`
1^
1[
0Q
0N
0K
b1001101 w
1i
18
1&
#700000
0!
0'
#710000
1!
1'
b1 I
1H
0G
1r
0q
b10101 s
1.
1,
0*
1#!
0!!
0{
1x
1y
b1001011 t
0;
19
1:
0`
1_
0^
0[
1Q
1N
1K
b1010000 w
0i
0g
0f
1e
08
06
05
14
0&
0$
0#
#720000
0!
0'
#730000
1!
1'
b10 I
0H
1G
0r
1q
b1000001 s
b1010000 t
b1010000 u
0Y
0X
0V
1U
0Q
0P
0N
1M
0.
0,
1*
0#!
1!!
0_
0x
0y
1{
b10 t
b1010001 w
09
0:
1;
1i
18
1&
0a
1]
1[
1P
0M
0K
b1010010 w
0i
1h
08
17
0&
1%
#740000
0!
0'
#750000
1!
1'
b1 I
1H
0G
1r
0q
b10101 s
1.
1,
0*
1#!
0!!
0{
1x
1y
b1010000 t
0;
19
1:
1a
1_
0]
0[
0P
1M
1K
b1010101 w
1i
0h
1g
18
07
16
1&
0%
1$
#760000
0!
0'
#770000
1!
1'
b10 I
0H
1G
0r
1q
b1000001 s
b1010101 t
b1010101 u
1Y
1W
1Q
1O
0.
0,
1*
0#!
1!!
0_
0x
0y
1{
b10 t
b1010110 w
09
0:
1;
0i
1h
08
17
0&
1%
1_
1]
1[
0Q
1P
0O
0M
0K
b1010111 w
1i
18
1&
#780000
0!
0