rtl/control.v
`timescale 1ns / 1ps

module control (
    input  wire [7:0] instr,
    output reg  reg_write,
    output reg  alu_src,
    output reg  [2:0] alu_op,
    output reg  jump,
    output reg  branch_z,
    output reg  halt
);

    wire [3:0] opcode = instr[7:4];

    always @(*) begin
        reg_write = 0;
        alu_src = 0;
        alu_op = 3'b000;
        jump = 0;
        branch_z = 0;
        halt = 0;

        case (opcode)
            4'b0001: begin // LDI
                reg_write = 1;
                alu_src = 1;
                alu_op = 3'b000;
            end
            4'b0010: begin // ADD
                reg_write = 1;
                alu_op = 3'b000;
            end
            4'b0011: begin // SUB
                reg_write = 1;
                alu_op = 3'b001;
            end
            4'b0100: jump = 1;         // JMP
            4'b0101: branch_z = 1;     // BRZ
            4'b1111: halt = 1;         // HALT
            default: ;                 // NOP
        endcase
    end

endmodule

rtl/alu.v
module alu (
    input  wire [7:0] a,
    input  wire [7:0] b,
    input  wire [2:0] alu_op,
    output reg  [7:0] result,
    output wire       zero,
    output wire       negative,
    output wire       carry_out
);

    reg [8:0] temp; // extra bit for carry

    always @(*) begin
        case (alu_op)
            3'b000: temp = a + b;             // ADD
            3'b001: temp = {1'b0, a} - b;     // SUB
            3'b010: temp = {1'b0, a & b};
            3'b011: temp = {1'b0, a | b};
            3'b100: temp = {1'b0, ~a};
            3'b101: temp = {8'b0, (a < b)};
            3'b110: temp = {1'b0, a << 1};
            3'b111: temp = {1'b0, a >> 1};
            default: temp = 9'b0;
        endcase
        result = temp[7:0];
    end

    assign zero = (result == 8'd0);
    assign negative = result[7];
    assign carry_out = temp[8];
endmodule

/*`timescale 1ns / 1ps

module alu (
    input  wire [7:0] a,
    input  wire [7:0] b,
    input  wire [2:0] alu_op,
    output reg  [7:0] result,
    output wire       zero,
);

    always @(*) begin
        case (alu_op)
            3'b000: result = a + b;    // ADD
            3'b001: result = a - b;    // SUB
            3'b010: result = a & b;    // AND
            3'b011: result = a | b;    // OR
            3'b100: result = ~a;       // NOT
            3'b101: result = (a < b) ? 8'd1 : 8'd0; // LT
            3'b110: result = a << 1;   // SHL
            3'b111: result = a >> 1;   // SHR
            default: result = 8'd0;
        endcase
    end

    assign zero = (result == 8'd0);

endmodule*/

rtl/registerfile.v
`timescale 1ns / 1ps

module register_file (
    input  wire clk,
    input  wire reset,
    input  wire write_enable,
    input  wire [1:0] write_addr,
    input  wire [7:0] write_data,
    input  wire [1:0] read_addr1,
    input  wire [1:0] read_addr2,
    output reg  [7:0] read_data1,
    output reg  [7:0] read_data2
);

    reg [7:0] registers [0:3];

    integer i;
    always @(posedge clk or posedge reset) begin
        if (reset) begin
            for (i = 0; i < 4; i = i + 1)
                registers[i] <= 0;
        end else if (write_enable) begin
            registers[write_addr] <= write_data;
        end
    end

    always @(*) begin
        read_data1 = registers[read_addr1];
        read_data2 = registers[read_addr2];
    end

endmodule

rtl/memory.v
`timescale 1ns / 1ps

module memory (
    input  wire [7:0] addr,
    output reg  [7:0] data_out
);

    reg [7:0] mem [0:255];

    //add testing
    /*initial begin
        mem[0] = 8'b00010001; // LDI R0, 1
        mem[1] = 8'b00010101; // LDI R1, 5
        mem[2] = 8'b00100001; // ADD R0, R1
        mem[3] = 8'b11110000; // HALT
    end*/

    //branch testing doesn't branch
    initial begin
        mem[0] = 8'b00010010; // LDI R0, 2
        mem[1] = 8'b00010100; // LDI R1, 4
        mem[2] = 8'b00100001; // ADD R0, R1 -> R0 = 6
        mem[3] = 8'b00110001; // SUB R0, R1 -> R0 = 2
        mem[4] = 8'b01010010; // BRZ 2 (should not branch)
        mem[5] = 8'b00011011; // LDI R2, 3
        mem[6] = 8'b00011100; // LDI R3, 4
        mem[7] = 8'b01010100; // BRZ 4 (should not branch)
        mem[8] = 8'b11110000; // HALT
    end

    //jump testing
    /*initial begin
        mem[0] = 8'b01000010; // JMP 2
        mem[1] = 8'b00010001; // LDI R0, 1 (should be skipped)
        mem[2] = 8'b00010011; // LDI R0, 3
        mem[3] = 8'b11110000; // HALT
    end*/

    //brz test branches
    /*initial begin
        mem[0] = 8'b00010000; // LDI R0, 0
        mem[1] = 8'b01010010; // BRZ 2 (should branch to PC=2)
        mem[2] = 8'b00010011; // LDI R0, 3
        mem[3] = 8'b11110000; // HALT

    end*/

    //final test1:
    /*initial begin
        mem[0] = 8'b00010010; // LDI R0, 2
        mem[1] = 8'b01010011; // BRZ 3 (should not branch, R0 ≠ 0)
        mem[2] = 8'b00010100; // LDI R1, 4 (should execute)
        mem[3] = 8'b11110000; // HALT
    end*/

    //final test2:
    /*initial begin
        mem[0] = 8'b00010011; // LDI R0, 3
        mem[1] = 8'b00110000; // SUB R0, R0 -> R0 = 0
        mem[2] = 8'b01010011; // BRZ 3 (if zero, branch to HALT)
        mem[3] = 8'b11110000; // HALT
        mem[4] = 8'b01000001; // JMP 1 (loop back to SUB)
    end*/

    //final test3: AND OR doesn't work. Add the opcodes.
    /*initial begin
        mem[0] = 8'b00010010; // LDI R0, 2  (0010)
        mem[1] = 8'b00010101; // LDI R1, 5  (0101)
        mem[2] = 8'b01100001; // AND R0, R1 -> 0000
        mem[3] = 8'b01110001; // OR R0, R1 -> 0111
        mem[4] = 8'b11110000; // HALT
    end*/

    /*initial begin
        mem[0] = 8'b00010010; // LDI R0, 2  -> R0 = 0010
        mem[1] = 8'b00010101; // LDI R1, 5  -> R1 = 0101
        mem[2] = 8'b01110001; // OR R0, R1 -> 0010 | 0101 = 0111
        mem[3] = 8'b11110000; // HALT
    end*/

    //STL, NOT test
    /*initial begin
        mem[0] = 8'b00010001; // LDI R0, 1
        mem[1] = 8'b00010100; // LDI R1, 4
        mem[2] = 8'b10010001; // SLT R0, R1 -> R0 < R1 -> R0 = 1
        mem[3] = 8'b10000000; // NOT R0 -> ~00000001 = 11111110
        mem[4] = 8'b11110000; // HALT
    end*/

    //Shift test
    /*initial begin
        mem[0] = 8'b00010001; // LDI R0, 1   (00000001)
        mem[1] = 8'b10100000; // SHL R0      -> 00000010
        mem[2] = 8'b10110000; // SHR R0      -> 00000001
        mem[3] = 8'b11110000; // HALT
    end*/

    //Flag test
    /*initial begin
        mem[0] = 8'b00010000; // LDI R0, 0
        mem[1] = 8'b00110000; // SUB R0, R0 (result 0 -> Z=1)
        mem[2] = 8'b00010001; // LDI R0, 1
        mem[3] = 8'b00110000; // SUB R0, R0 (result 0 -> Z=1)
        mem[4] = 8'b11110000; // HALT
    end*/

    always @(*) begin
        data_out = mem[addr];
    end

endmodule

rtl/datapath.v
`timescale 1ns / 1ps

module datapath (
    input  wire clk,
    input  wire reset,
    input  wire reg_write,
    input  wire alu_src,
    input  wire [2:0] alu_op,
    input  wire jump,
    input  wire branch_z,
    input  wire halt,
    output wire [7:0] instr,
    output wire [7:0] result_out,
    output reg  [7:0] pc,
    output reg        z_flag,
    output reg        n_flag,
    output reg        c_flag
);

    wire [7:0] read1, read2, alu_b, alu_result;
    wire zero_flag, negative_flag, carry_flag;

    memory u_mem (
        .addr(pc),
        .data_out(instr)
    );

    register_file u_reg (
        .clk(clk),
        .reset(reset),
        .write_enable(reg_write),
        .write_addr(instr[3:2]),
        .write_data(alu_result),
        .read_addr1(instr[3:2]),
        .read_addr2(instr[1:0]),
        .read_data1(read1),
        .read_data2(read2)
    );

    alu u_alu (
        .a(read1),
        .b(alu_b),
        .alu_op(alu_op),
        .result(alu_result),
        .zero(zero_flag),
        .negative(negative_flag),
        .carry_out(carry_flag)
    );

    assign alu_b = alu_src ? {4'b0000, instr[3:0]} : read2;
    assign result_out = alu_result;

    always @(posedge clk or posedge reset) begin
        if (reset) begin
            pc <= 0;
            z_flag <= 0;
            n_flag <= 0;
            c_flag <= 0;
        end else begin
            // Update PC
            if (halt)
                pc <= pc; // freeze PC
            else if (jump)
                pc <= {4'b0000, instr[3:0]};
            else if (branch_z && z_flag)
                pc <= {4'b0000, instr[3:0]};
            else
                pc <= pc + 1;

            // Update flags after ALU operation
            z_flag <= zero_flag;
            n_flag <= negative_flag;
            c_flag <= carry_flag;
        end
    end

endmodule

/*`timescale 1ns / 1ps

module datapath (
    input  wire clk,
    input  wire reset,
    input  wire reg_write,
    input  wire alu_src,
    input  wire [2:0] alu_op,
    input  wire jump,
    input  wire branch_z,
    input  wire halt,
    output wire [7:0] instr,
    output wire [7:0] result_out,
    output reg  [7:0] pc
);

    wire [7:0] read1, read2, alu_b, alu_result;
    wire zero_flag;

    memory u_mem (
        .addr(pc),
        .data_out(instr)
    );

    register_file u_reg (
        .clk(clk),
        .reset(reset),
        .write_enable(reg_write),
        .write_addr(instr[3:2]),
        .write_data(alu_result),
        .read_addr1(instr[3:2]),
        .read_addr2(instr[1:0]),
        .read_data1(read1),
        .read_data2(read2)
    );

    alu u_alu (
        .a(read1),
        .b(alu_b),
        .alu_op(alu_op),
        .result(alu_result),
        .zero(zero_flag)
    );

    assign alu_b = alu_src ? {4'b0000, instr[3:0]} : read2;
    assign result_out = alu_result;

    always @(posedge clk or posedge reset) begin
        if (reset)
            pc <= 0;
        else if (halt)
            pc <= pc; // freeze PC
        else if (jump)
            pc <= {4'b0000, instr[3:0]};
        else if (branch_z && zero_flag)
            pc <= {4'b0000, instr[3:0]};
        else
            pc <= pc + 1;
    end

endmodule*/

rtl/top.v
module top (
    input  wire clk,
    input  wire reset,
    output wire [3:0] led_out
);

    wire [7:0] instr;
    wire [7:0] result_out;
    wire reg_write, alu_src, jump, branch_z, halt;
    wire [2:0] alu_op;
    wire [7:0] pc_debug;

    datapath u_datapath (
        .clk(clk),
        .reset(reset),
        .reg_write(reg_write),
        .alu_src(alu_src),
        .alu_op(alu_op),
        .jump(jump),
        .branch_z(branch_z),
        .halt(halt),
        .instr(instr),
        .result_out(result_out),
        .pc(pc_debug)
    );

    control u_control (
        .instr(instr),
        .reg_write(reg_write),
        .alu_src(alu_src),
        .alu_op(alu_op),
        .jump(jump),
        .branch_z(branch_z),
        .halt(halt)
    );

    //assign led_out = result_out[3:0];
    assign led_out = halt ? 4'b0000 : result_out[3:0];


endmodule

sim/top_tb.v
`timescale 1ns / 1ps

module top_tb;

    reg clk = 0;
    reg reset = 1;
    wire [3:0] led_out;

    top uut (
        .clk(clk),
        .reset(reset),
        .led_out(led_out)
    );

    always #10 clk = ~clk;

    initial begin
        $dumpfile("cpu_waveform.vcd");
        $dumpvars(0, top_tb);

        #100 reset = 0;
        #1000;

        $finish;
    end

    always @(posedge clk) begin
        $display("PC=%h | Instr=%b | LEDs=%b", uut.u_datapath.pc, uut.u_datapath.instr, led_out);
        
        if (uut.halt) begin
            $display("PC=%h | Instr=%b | LEDs=%b | Z=%b N=%b C=%b", uut.u_datapath.pc, uut.u_datapath.instr, led_out, uut.u_datapath.z_flag, uut.u_datapath.n_flag, uut.u_datapath.c_flag);
            $display("HALT detected at PC=%h, stopping simulation.", uut.u_datapath.pc);
            $finish;
        end
    end


endmodule

modelsim/cpu_waveform.vcd
$date
	Tue Jun 24 21:02:00 2025
$end
$version
	ModelSim Version 2020.1
$end
$timescale
	1ps
$end

$scope module top_tb $end
$var reg 1 ! clk $end
$var reg 1 " reset $end
$var wire 1 # led_out [3] $end
$var wire 1 $ led_out [2] $end
$var wire 1 % led_out [1] $end
$var wire 1 & led_out [0] $end

$scope module uut $end
$var wire 1 ' clk $end
$var wire 1 ( reset $end
$var wire 1 # led_out [3] $end
$var wire 1 $ led_out [2] $end
$var wire 1 % led_out [1] $end
$var wire 1 & led_out [0] $end
$var wire 1 ) instr [7] $end
$var wire 1 * instr [6] $end
$var wire 1 + instr [5] $end
$var wire 1 , instr [4] $end
$var wire 1 - instr [3] $end
$var wire 1 . instr [2] $end
$var wire 1 / instr [1] $end
$var wire 1 0 instr [0] $end
$var wire 1 1 result_out [7] $end
$var wire 1 2 result_out [6] $end
$var wire 1 3 result_out [5] $end
$var wire 1 4 result_out [4] $end
$var wire 1 5 result_out [3] $end
$var wire 1 6 result_out [2] $end
$var wire 1 7 result_out [1] $end
$var wire 1 8 result_out [0] $end
$var wire 1 9 reg_write $end
$var wire 1 : alu_src $end
$var wire 1 ; jump $end
$var wire 1 < branch_z $end
$var wire 1 = halt $end
$var wire 1 > alu_op [2] $end
$var wire 1 ? alu_op [1] $end
$var wire 1 @ alu_op [0] $end
$var wire 1 A pc_debug [7] $end
$var wire 1 B pc_debug [6] $end
$var wire 1 C pc_debug [5] $end
$var wire 1 D pc_debug [4] $end
$var wire 1 E pc_debug [3] $end
$var wire 1 F pc_debug [2] $end
$var wire 1 G pc_debug [1] $end
$var wire 1 H pc_debug [0] $end

$scope module u_datapath $end
$var wire 1 ' clk $end
$var wire 1 ( reset $end
$var wire 1 9 reg_write $end
$var wire 1 : alu_src $end
$var wire 1 > alu_op [2] $end
$var wire 1 ? alu_op [1] $end
$var wire 1 @ alu_op [0] $end
$var wire 1 ; jump $end
$var wire 1 < branch_z $end
$var wire 1 = halt $end
$var wire 1 ) instr [7] $end
$var wire 1 * instr [6] $end
$var wire 1 + instr [5] $end
$var wire 1 , instr [4] $end
$var wire 1 - instr [3] $end
$var wire 1 . instr [2] $end
$var wire 1 / instr [1] $end
$var wire 1 0 instr [0] $end
$var wire 1 1 result_out [7] $end
$var wire 1 2 result_out [6] $end
$var wire 1 3 result_out [5] $end
$var wire 1 4 result_out [4] $end
$var wire 1 5 result_out [3] $end
$var wire 1 6 result_out [2] $end
$var wire 1 7 result_out [1] $end
$var wire 1 8 result_out [0] $end
$var reg 8 I pc [7:0] $end
$var reg 1 J z_flag $end
$var reg 1 K n_flag $end
$var reg 1 L c_flag $end
$var wire 1 M read1 [7] $end
$var wire 1 N read1 [6] $end
$var wire 1 O read1 [5] $end
$var wire 1 P read1 [4] $end
$var wire 1 Q read1 [3] $end
$var wire 1 R read1 [2] $end
$var wire 1 S read1 [1] $end
$var wire 1 T read1 [0] $end
$var wire 1 U read2 [7] $end
$var wire 1 V read2 [6] $end
$var wire 1 W read2 [5] $end
$var wire 1 X read2 [4] $end
$var wire 1 Y read2 [3] $end
$var wire 1 Z read2 [2] $end
$var wire 1 [ read2 [1] $end
$var wire 1 \ read2 [0] $end
$var wire 1 ] alu_b [7] $end
$var wire 1 ^ alu_b [6] $end
$var wire 1 _ alu_b [5] $end
$var wire 1 ` alu_b [4] $end
$var wire 1 a alu_b [3] $end
$var wire 1 b alu_b [2] $end
$var wire 1 c alu_b [1] $end
$var wire 1 d alu_b [0] $end
$var wire 1 e alu_result [7] $end
$var wire 1 f alu_result [6] $end
$var wire 1 g alu_result [5] $end
$var wire 1 h alu_result [4] $end
$var wire 1 i alu_result [3] $end
$var wire 1 j alu_result [2] $end
$var wire 1 k alu_result [1] $end
$var wire 1 l alu_result [0] $end
$var wire 1 m zero_flag $end
$var wire 1 n negative_flag $end
$var wire 1 o carry_flag $end

$scope module u_mem $end
$var wire 1 p addr [7] $end
$var wire 1 q addr [6] $end
$var wire 1 r addr [5] $end
$var wire 1 s addr [4] $end
$var wire 1 t addr [3] $end
$var wire 1 u addr [2] $end
$var wire 1 v addr [1] $end
$var wire 1 w addr [0] $end
$var reg 8 x data_out [7:0] $end
$upscope $end

$scope module u_reg $end
$var wire 1 ' clk $end
$var wire 1 ( reset $end
$var wire 1 9 write_enable $end
$var wire 1 - write_addr [1] $end
$var wire 1 . write_addr [0] $end
$var wire 1 e write_data [7] $end
$var wire 1 f write_data [6] $end
$var wire 1 g write_data [5] $end
$var wire 1 h write_data [4] $end
$var wire 1 i write_data [3] $end
$var wire 1 j write_data [2] $end
$var wire 1 k write_data [1] $end
$var wire 1 l write_data [0] $end
$var wire 1 - read_addr1 [1] $end
$var wire 1 . read_addr1 [0] $end
$var wire 1 / read_addr2 [1] $end
$var wire 1 0 read_addr2 [0] $end
$var reg 8 y read_data1 [7:0] $end
$var reg 8 z read_data2 [7:0] $end
$var integer 32 { i $end
$upscope $end

$scope module u_alu $end
$var wire 1 M a [7] $end
$var wire 1 N a [6] $end
$var wire 1 O a [5] $end
$var wire 1 P a [4] $end
$var wire 1 Q a [3] $end
$var wire 1 R a [2] $end
$var wire 1 S a [1] $end
$var wire 1 T a [0] $end
$var wire 1 ] b [7] $end
$var wire 1 ^ b [6] $end
$var wire 1 _ b [5] $end
$var wire 1 ` b [4] $end
$var wire 1 a b [3] $end
$var wire 1 b b [2] $end
$var wire 1 c b [1] $end
$var wire 1 d b [0] $end
$var wire 1 > alu_op [2] $end
$var wire 1 ? alu_op [1] $end
$var wire 1 @ alu_op [0] $end
$var reg 8 | result [7:0] $end
$var wire 1 m zero $end
$var wire 1 n negative $end
$var wire 1 o carry_out $end
$var reg 9 } temp [8:0] $end
$upscope $end
$upscope $end

$scope module u_control $end
$var wire 1 ) instr [7] $end
$var wire 1 * instr [6] $end
$var wire 1 + instr [5] $end
$var wire 1 , instr [4] $end
$var wire 1 - instr [3] $end
$var wire 1 . instr [2] $end
$var wire 1 / instr [1] $end
$var wire 1 0 instr [0] $end
$var reg 1 ~ reg_write $end
$var reg 1 !! alu_src $end
$var reg 3 "! alu_op [2:0] $end
$var reg 1 #! jump $end
$var reg 1 $! branch_z $end
$var reg 1 %! halt $end
$var wire 1 &! opcode [3] $end
$var wire 1 '! opcode [2] $end
$var wire 1 (! opcode [1] $end
$var wire 1 )! opcode [0] $end
$upscope $end
$upscope $end
$upscope $end
$enddefinitions $end
#0
$dumpvars
0!
1"
b0 I
0J
0K
0L
b10010 x
b0 y
b0 z
b10 |
b10 }
1~
1!!
b0 "!
0#!
0$!
0%!
b100 {
0&
1%
0$
0#
00
1/
0.
0-
1,
0+
0*
0)
08
17
06
05
04
03
02
01
19
1:
0;
0<
0=
0@
0?
0>
0H
0G
0F
0E
0D
0C
0B
0A
0T
0S
0R
0Q
0P
0O
0N
0M
0\
0[
0Z
0Y
0X
0W
0V
0U
0d
1c
0b
0a
0`
0_
0^
0]
0l
1k
0j
0i
0h
0g
0f
0e
0m
0n
0o
1)!
0(!
0'!
0&!
1(
0'
0w
0v
0u
0t
0s
0r
0q
0p
$end
#10000
1!
1'
b0 {
b1 {
b10 {
b11 {
b100 {
#20000
0!
0'
#30000
1!
1'
b0 {
b1 {
b10 {
b11 {
b100 {
#40000
0!
0'
#50000
1!
1'
b0 {
b1 {
b10 {
b11 {
b100 {
#60000
0!
0'
#70000
1!
1'
b0 {
b1 {
b10 {
b11 {
b100 {
#80000
0!
0'
#90000
1!
1'
b0 {
b1 {
b10 {
b11 {
b100 {
#100000
0"
0!
0(
0'
#110000
1!
1'
b1 I
1H
1w
b10100 x
b10 y
1S
0/
1.
0c
1b
b0 y
b10 z
b110 }
b110 |
1j
1[
16
1$
0S
b100 }
b100 |
0k
07
0%
#120000
0!
0'
#130000
1!
1'
b10 I
0H
1G
0w
1v
b100001 x
b100 y
1R
10
0.
0,
1+
0)!
1(!
1d
0b
0~
0!!
1~
b10 y
b100 z
b101 }
b101 |
0:
1l
0[
1Z
18
1&
0d
1b
1S
0R
b110 }
b110 |
0l
1k
08
17
0&
1%
#140000
0!
0'
#150000
1!
1'
b11 I
1H
1w
b110001 x
b110 y
1R
1,
1)!
0~
1~
b1 "!
b1010 }
b1010 |
0j
1i
06
15
0$
1#
1@
b10 }
b10 |
0i
05
0#
#160000
0!
0'
#170000
1!
1'
b100 I
0H
0G
1F
0w
0v
1u
b1010010 x
b10 y
0R
00
1/
0+
1*
0(!
1'!
0~
b0 "!
1$!
b0 z
b111111110 }
b11111110 |
1n
1o
09
1<
1j
1i
1h
1g
1f
1e
0Z
16
15
14
13
12
11
1$
1#
0b
0@
b10 }
b10 |
0n
0o
0j
0i
0h
0g
0f
0e
06
05
04
03
02
01
0$
0#
#180000
0!
0'
#190000
1!
1'
b101 I
1H
1w
b11011 x
10
1-
0*
0'!
0$!
1~
1!!
b0 y
0<
19
1:
1d
1c
1a
0S
b1011 }
b1011 |
1l
1i
18
15
1&
1#
#200000
0!
0'
#210000
1!
1'
b110 I
0H
1G
0w
1v
b11100 x
b1011 y
1T
1S
1Q
00
0/
1.
0d
0c
1b
b0 y
b10 z
b10111 }
b10111 |
1j
0i
1h
1[
16
05
14
1$
0#
0T
0S
0Q
b1100 }
b1100 |
0l
0k
1i
0h
08
07
15
04
0&
0%
1#
#220000
0!
0'
#230000
1!
1'
b111 I
1H
1w
b1010100 x
b1100 y
1R
1Q
0-
1*
1'!
0a
0~
0!!
1$!
b100 y
b10000 }
b10000 |
09
0:
1<
0j
0i
1h
06
05
14
0$
0#
1c
0b
0Q
b110 }
b110 |
1k
1j
0h
17
16
04
1%
1$
#240000
0!
0'
#250000
1!
1'
b1000 I
0H
0G
0F
1E
0w
0v
0u
1t
b11110000 x
0.
1+
1)
1(!
1&!
0$!
1%!
b10 y
0<
1=
0%
0$
1S
0R
b100 }
b100 |
0k
07
