rtl/control.v
`timescale 1ns / 1ps

module control (
    input  wire [7:0] instr,
    output reg  reg_write,
    output reg  alu_src,
    output reg  [2:0] alu_op,
    output reg  jump,
    output reg  branch_z,
    output reg branch_n,
    output reg branch_c,
    output reg  halt
);

    wire [3:0] opcode = instr[7:4];

    always @(*) begin
        reg_write = 0;
        alu_src = 0;
        alu_op = 3'b000;
        jump = 0;
        branch_z = 0;
        branch_n = 0;
        branch_c = 0;
        halt = 0;

        case (opcode)
            4'b0001: begin // LDI
                reg_write = 1;
                alu_src = 1;
                alu_op = 3'b000;
            end
            4'b0010: begin // ADD
                reg_write = 1;
                alu_op = 3'b000;
            end
            4'b0011: begin // SUB
                reg_write = 1;
                alu_op = 3'b001;
            end
            4'b0100: jump = 1;         // JMP
            4'b0101: branch_z = 1;     // BRZ
            4'b0110: begin // AND
                reg_write = 1;
                alu_op = 3'b010;
            end
            4'b0111: begin // OR
                reg_write = 1;
                alu_op = 3'b011;
            end
            4'b1000: begin // NOT
                reg_write = 1;
                alu_op = 3'b100;
            end
            4'b1001: begin // LT
                reg_write = 1;
                alu_op = 3'b101;
            end
            4'b1010: begin // SHL
                reg_write = 1;
                alu_op = 3'b110;
            end
            4'b1011: begin // SHR
                reg_write = 1;
                alu_op = 3'b111;
            end
            4'b1100: branch_n = 1;     //BRN
            4'b1101: branch_c = 1;     //BRC
            4'b1111: halt = 1;         // HALT
            default: ;                 // NOP
        endcase
    end

endmodule

rtl/alu.v
module alu (
    input  wire [7:0] a,
    input  wire [7:0] b,
    input  wire [2:0] alu_op,
    output reg  [7:0] result,
    output wire       zero,
    output wire       negative,
    output wire       carry_out
);

    reg [8:0] temp; // extra bit for carry

    always @(*) begin
        case (alu_op)
            3'b000: temp = a + b;             // ADD
            3'b001: temp = {1'b0, a} - b;     // SUB
            3'b010: temp = {1'b0, a & b};     // AND
            3'b011: temp = {1'b0, a | b};     // OR
            3'b100: temp = {1'b0, ~a};        // NOT
            3'b101: temp = {8'b0, (a < b)};   // SLT
            3'b110: temp = {1'b0, a << 1};    // SHL
            3'b111: temp = {1'b0, a >> 1};    // SHR
            default: temp = 9'b0;
        endcase
        result = temp[7:0];
    end

    assign zero = (result == 8'd0);
    assign negative = result[7];
    assign carry_out = temp[8];
endmodule

/*`timescale 1ns / 1ps

module alu (
    input  wire [7:0] a,
    input  wire [7:0] b,
    input  wire [2:0] alu_op,
    output reg  [7:0] result,
    output wire       zero,
);

    always @(*) begin
        case (alu_op)
            3'b000: result = a + b;    // ADD
            3'b001: result = a - b;    // SUB
            3'b010: result = a & b;    // AND
            3'b011: result = a | b;    // OR
            3'b100: result = ~a;       // NOT
            3'b101: result = (a < b) ? 8'd1 : 8'd0; // LT
            3'b110: result = a << 1;   // SHL
            3'b111: result = a >> 1;   // SHR
            default: result = 8'd0;
        endcase
    end

    assign zero = (result == 8'd0);

endmodule*/

rtl/registerfile.v
`timescale 1ns / 1ps

module registerfile (
    input  wire clk,
    input  wire reset,
    input  wire write_enable,
    input  wire [1:0] write_addr,
    input  wire [7:0] write_data,
    input  wire [1:0] read_addr1,
    input  wire [1:0] read_addr2,
    output reg  [7:0] read_data1,
    output reg  [7:0] read_data2
);

    reg [7:0] registers [0:3];

    integer i;
    always @(posedge clk or posedge reset) begin
        if (reset) begin
            for (i = 0; i < 4; i = i + 1)
                registers[i] <= 0;
        end else if (write_enable) begin
            registers[write_addr] <= write_data;
        end
    end

    always @(*) begin
        read_data1 = registers[read_addr1];
        read_data2 = registers[read_addr2];
    end

endmodule

rtl/memory.v
`timescale 1ns / 1ps

module memory (
    input  wire [7:0] addr,
    output reg  [7:0] data_out
);

    reg [7:0] mem [0:255];

    initial begin
        mem[0] = 8'b00010001; // LDI R0, 1
        mem[1] = 8'b00010101; // LDI R1, 5
        mem[2] = 8'b00100001; // ADD R0, R1
        mem[3] = 8'b11110000; // HALT
    end

    /*initial begin
        mem[0] = 8'b00010010; // LDI R0, 2
        mem[1] = 8'b00010100; // LDI R1, 4
        mem[2] = 8'b00100001; // ADD R0, R1 -> R0 = 6
        mem[3] = 8'b00110001; // SUB R0, R1 -> R0 = 2
        mem[4] = 8'b01000001; // AND R0, R1 -> R0 = 0
        mem[5] = 8'b01010001; // OR R0, R1 -> R0 = 4
        mem[6] = 8'b01010111; // BRZ to 7 (should not branch because R0 ≠ 0)
        mem[7] = 8'b00011011; // LDI R2, 3
        mem[8] = 8'b01000100; // JMP to 4 (loop or test jump)
        mem[9] = 8'b11110000; // HALT (unreachable in this case)
    end*/

    always @(*) begin
        data_out = mem[addr];
    end

endmodule

rtl/datapath.v
`timescale 1ns / 1ps

module datapath (
    input  wire clk,
    input  wire reset,
    input  wire reg_write,
    input  wire alu_src,
    input  wire [2:0] alu_op,
    input  wire jump,
    input  wire branch_z,
    input wire branch_n,
    input wire branch_c,
    input  wire halt,
    output wire [7:0] instr,
    output wire [7:0] result_out,
    output reg  [7:0] pc,
    output reg        z_flag,
    output reg        n_flag,
    output reg        c_flag
);

    wire [7:0] read1, read2, alu_b, alu_result;
    wire zero_flag, negative_flag, carry_flag;

    memory u_mem (
        .addr(pc),
        .data_out(instr)
    );

    registerfile u_reg (
        .clk(clk),
        .reset(reset),
        .write_enable(reg_write),
        .write_addr(instr[3:2]),
        .write_data(alu_result),
        .read_addr1(instr[3:2]),
        .read_addr2(instr[1:0]),
        .read_data1(read1),
        .read_data2(read2)
    );

    alu u_alu (
        .a(read1),
        .b(alu_b),
        .alu_op(alu_op),
        .result(alu_result),
        .zero(zero_flag),
        .negative(negative_flag),
        .carry_out(carry_flag)
    );

    assign alu_b = alu_src ? {4'b0000, instr[3:0]} : read2;
    assign result_out = alu_result;

    always @(posedge clk or posedge reset) begin
        if (reset) begin
            pc <= 0;
            z_flag <= 0;
            n_flag <= 0;
            c_flag <= 0;
        end else begin
            // Update PC
            if (halt)
                pc <= pc; // freeze PC
            else if (jump)
                pc <= {4'b0000, instr[3:0]};
            else if (branch_z && z_flag)
                pc <= {4'b0000, instr[3:0]};
            else if (branch_n && n_flag)
                pc <= {4'b0000, instr[3:0]};
            else if (branch_c && c_flag)
                pc <= {4'b0000, instr[3:0]};
            else
                pc <= pc + 1;

            // Update flags after ALU operation
            z_flag <= zero_flag;
            n_flag <= negative_flag;
            c_flag <= carry_flag;
        end
    end

endmodule

rtl/top.v
module top (
    input  wire clk,
    input  wire reset,
    output wire [3:0] led_out
);

    wire [7:0] instr;
    wire [7:0] result_out;
    wire reg_write, alu_src, jump, branch_z, branch_n, branch_c, halt;
    wire [2:0] alu_op;
    wire [7:0] pc_debug;

    wire z_flag, n_flag, c_flag;

    datapath u_datapath (
        .clk(clk),
        .reset(reset),
        .reg_write(reg_write),
        .alu_src(alu_src),
        .alu_op(alu_op),
        .jump(jump),
        .branch_z(branch_z),
        .branch_n(branch_n),
        .branch_c(branch_c),
        .halt(halt),
        .instr(instr),
        .result_out(result_out),
        .pc(pc_debug),
        .z_flag(z_flag),
        .n_flag(n_flag),
        .c_flag(c_flag)
    );

    control u_control (
        .instr(instr),
        .reg_write(reg_write),
        .alu_src(alu_src),
        .alu_op(alu_op),
        .jump(jump),
        .branch_z(branch_z),
        .branch_n(branch_n),
        .branch_c(branch_c),
        .halt(halt)
    );

    assign led_out = result_out[3:0];
    //assign led_out = halt ? 4'b0000 : result_out[3:0];


endmodule

sim/top_tb.v
`timescale 1ns / 1ps

module top_tb;

    reg clk = 0;
    reg reset = 1;
    wire [3:0] led_out;

    top uut (
        .clk(clk),
        .reset(reset),
        .led_out(led_out)
    );

    always #10 clk = ~clk;

    initial begin
        $dumpfile("cpu_waveform.vcd");
        $dumpvars(0, top_tb);

        #100 reset = 0;
        #1000;

        $finish;
    end

    always @(posedge clk) begin
        //$display("PC=%h | Instr=%b | LEDs=%b", uut.u_datapath.pc, uut.u_datapath.instr, led_out);
        $display("PC=%h | Instr=%b | LEDs=%b | Z=%b N=%b C=%b", uut.u_datapath.pc, uut.u_datapath.instr, led_out, uut.u_datapath.z_flag, uut.u_datapath.n_flag, uut.u_datapath.c_flag);
        if (uut.halt) begin
            $display("HALT detected at PC=%h, stopping simulation.", uut.u_datapath.pc);
            $finish;
        end
    end


endmodule

modelsim/cpu_waveform.vcd
$date
	Wed Jun 25 13:45:02 2025
$end
$version
	ModelSim Version 2020.1
$end
$timescale
	1ps
$end

$scope module top_tb $end
$var reg 1 ! clk $end
$var reg 1 " reset $end
$var wire 1 # led_out [3] $end
$var wire 1 $ led_out [2] $end
$var wire 1 % led_out [1] $end
$var wire 1 & led_out [0] $end

$scope module uut $end
$var wire 1 ' clk $end
$var wire 1 ( reset $end
$var wire 1 # led_out [3] $end
$var wire 1 $ led_out [2] $end
$var wire 1 % led_out [1] $end
$var wire 1 & led_out [0] $end
$var wire 1 ) instr [7] $end
$var wire 1 * instr [6] $end
$var wire 1 + instr [5] $end
$var wire 1 , instr [4] $end
$var wire 1 - instr [3] $end
$var wire 1 . instr [2] $end
$var wire 1 / instr [1] $end
$var wire 1 0 instr [0] $end
$var wire 1 1 result_out [7] $end
$var wire 1 2 result_out [6] $end
$var wire 1 3 result_out [5] $end
$var wire 1 4 result_out [4] $end
$var wire 1 5 result_out [3] $end
$var wire 1 6 result_out [2] $end
$var wire 1 7 result_out [1] $end
$var wire 1 8 result_out [0] $end
$var wire 1 9 reg_write $end
$var wire 1 : alu_src $end
$var wire 1 ; jump $end
$var wire 1 < branch_z $end
$var wire 1 = branch_n $end
$var wire 1 > branch_c $end
$var wire 1 ? halt $end
$var wire 1 @ alu_op [2] $end
$var wire 1 A alu_op [1] $end
$var wire 1 B alu_op [0] $end
$var wire 1 C pc_debug [7] $end
$var wire 1 D pc_debug [6] $end
$var wire 1 E pc_debug [5] $end
$var wire 1 F pc_debug [4] $end
$var wire 1 G pc_debug [3] $end
$var wire 1 H pc_debug [2] $end
$var wire 1 I pc_debug [1] $end
$var wire 1 J pc_debug [0] $end
$var wire 1 K z_flag $end
$var wire 1 L n_flag $end
$var wire 1 M c_flag $end

$scope module u_datapath $end
$var wire 1 ' clk $end
$var wire 1 ( reset $end
$var wire 1 9 reg_write $end
$var wire 1 : alu_src $end
$var wire 1 @ alu_op [2] $end
$var wire 1 A alu_op [1] $end
$var wire 1 B alu_op [0] $end
$var wire 1 ; jump $end
$var wire 1 < branch_z $end
$var wire 1 = branch_n $end
$var wire 1 > branch_c $end
$var wire 1 ? halt $end
$var wire 1 ) instr [7] $end
$var wire 1 * instr [6] $end
$var wire 1 + instr [5] $end
$var wire 1 , instr [4] $end
$var wire 1 - instr [3] $end
$var wire 1 . instr [2] $end
$var wire 1 / instr [1] $end
$var wire 1 0 instr [0] $end
$var wire 1 1 result_out [7] $end
$var wire 1 2 result_out [6] $end
$var wire 1 3 result_out [5] $end
$var wire 1 4 result_out [4] $end
$var wire 1 5 result_out [3] $end
$var wire 1 6 result_out [2] $end
$var wire 1 7 result_out [1] $end
$var wire 1 8 result_out [0] $end
$var reg 8 N pc [7:0] $end
$var reg 1 O z_flag $end
$var reg 1 P n_flag $end
$var reg 1 Q c_flag $end
$var wire 1 R read1 [7] $end
$var wire 1 S read1 [6] $end
$var wire 1 T read1 [5] $end
$var wire 1 U read1 [4] $end
$var wire 1 V read1 [3] $end
$var wire 1 W read1 [2] $end
$var wire 1 X read1 [1] $end
$var wire 1 Y read1 [0] $end
$var wire 1 Z read2 [7] $end
$var wire 1 [ read2 [6] $end
$var wire 1 \ read2 [5] $end
$var wire 1 ] read2 [4] $end
$var wire 1 ^ read2 [3] $end
$var wire 1 _ read2 [2] $end
$var wire 1 ` read2 [1] $end
$var wire 1 a read2 [0] $end
$var wire 1 b alu_b [7] $end
$var wire 1 c alu_b [6] $end
$var wire 1 d alu_b [5] $end
$var wire 1 e alu_b [4] $end
$var wire 1 f alu_b [3] $end
$var wire 1 g alu_b [2] $end
$var wire 1 h alu_b [1] $end
$var wire 1 i alu_b [0] $end
$var wire 1 j alu_result [7] $end
$var wire 1 k alu_result [6] $end
$var wire 1 l alu_result [5] $end
$var wire 1 m alu_result [4] $end
$var wire 1 n alu_result [3] $end
$var wire 1 o alu_result [2] $end
$var wire 1 p alu_result [1] $end
$var wire 1 q alu_result [0] $end
$var wire 1 r zero_flag $end
$var wire 1 s negative_flag $end
$var wire 1 t carry_flag $end

$scope module u_mem $end
$var wire 1 u addr [7] $end
$var wire 1 v addr [6] $end
$var wire 1 w addr [5] $end
$var wire 1 x addr [4] $end
$var wire 1 y addr [3] $end
$var wire 1 z addr [2] $end
$var wire 1 { addr [1] $end
$var wire 1 | addr [0] $end
$var reg 8 } data_out [7:0] $end
$upscope $end

$scope module u_reg $end
$var wire 1 ' clk $end
$var wire 1 ( reset $end
$var wire 1 9 write_enable $end
$var wire 1 - write_addr [1] $end
$var wire 1 . write_addr [0] $end
$var wire 1 j write_data [7] $end
$var wire 1 k write_data [6] $end
$var wire 1 l write_data [5] $end
$var wire 1 m write_data [4] $end
$var wire 1 n write_data [3] $end
$var wire 1 o write_data [2] $end
$var wire 1 p write_data [1] $end
$var wire 1 q write_data [0] $end
$var wire 1 - read_addr1 [1] $end
$var wire 1 . read_addr1 [0] $end
$var wire 1 / read_addr2 [1] $end
$var wire 1 0 read_addr2 [0] $end
$var reg 8 ~ read_data1 [7:0] $end
$var reg 8 !! read_data2 [7:0] $end
$var integer 32 "! i $end
$upscope $end

$scope module u_alu $end
$var wire 1 R a [7] $end
$var wire 1 S a [6] $end
$var wire 1 T a [5] $end
$var wire 1 U a [4] $end
$var wire 1 V a [3] $end
$var wire 1 W a [2] $end
$var wire 1 X a [1] $end
$var wire 1 Y a [0] $end
$var wire 1 b b [7] $end
$var wire 1 c b [6] $end
$var wire 1 d b [5] $end
$var wire 1 e b [4] $end
$var wire 1 f b [3] $end
$var wire 1 g b [2] $end
$var wire 1 h b [1] $end
$var wire 1 i b [0] $end
$var wire 1 @ alu_op [2] $end
$var wire 1 A alu_op [1] $end
$var wire 1 B alu_op [0] $end
$var reg 8 #! result [7:0] $end
$var wire 1 r zero $end
$var wire 1 s negative $end
$var wire 1 t carry_out $end
$var reg 9 $! temp [8:0] $end
$upscope $end
$upscope $end

$scope module u_control $end
$var wire 1 ) instr [7] $end
$var wire 1 * instr [6] $end
$var wire 1 + instr [5] $end
$var wire 1 , instr [4] $end
$var wire 1 - instr [3] $end
$var wire 1 . instr [2] $end
$var wire 1 / instr [1] $end
$var wire 1 0 instr [0] $end
$var reg 1 %! reg_write $end
$var reg 1 &! alu_src $end
$var reg 3 '! alu_op [2:0] $end
$var reg 1 (! jump $end
$var reg 1 )! branch_z $end
$var reg 1 *! branch_n $end
$var reg 1 +! branch_c $end
$var reg 1 ,! halt $end
$var wire 1 -! opcode [3] $end
$var wire 1 .! opcode [2] $end
$var wire 1 /! opcode [1] $end
$var wire 1 0! opcode [0] $end
$upscope $end
$upscope $end
$upscope $end
$enddefinitions $end
#0
$dumpvars
0!
1"
b0 N
0O
0P
0Q
b10001 }
b0 ~
b0 !!
b1 #!
b1 $!
1%!
1&!
b0 '!
0(!
0)!
0*!
0+!
0,!
b100 "!
1&
0%
0$
0#
10
0/
0.
0-
1,
0+
0*
0)
18
07
06
05
04
03
02
01
19
1:
0;
0<
0=
0>
0?
0B
0A
0@
0J
0I
0H
0G
0F
0E
0D
0C
0K
0L
0M
0Y
0X
0W
0V
0U
0T
0S
0R
0a
0`
0_
0^
0]
0\
0[
0Z
1i
0h
0g
0f
0e
0d
0c
0b
1q
0p
0o
0n
0m
0l
0k
0j
0r
0s
0t
10!
0/!
0.!
0-!
1(
0'
0|
0{
0z
0y
0x
0w
0v
0u
$end
#10000
1!
1'
b0 "!
b1 "!
b10 "!
b11 "!
b100 "!
#20000
0!
0'
#30000
1!
1'
b0 "!
b1 "!
b10 "!
b11 "!
b100 "!
#40000
0!
0'
#50000
1!
1'
b0 "!
b1 "!
b10 "!
b11 "!
b100 "!
#60000
0!
0'
#70000
1!
1'
b0 "!
b1 "!
b10 "!
b11 "!
b100 "!
#80000
0!
0'
#90000
1!
1'
b0 "!
b1 "!
b10 "!
b11 "!
b100 "!
#100000
0"
0!
0(
0'
#110000
1!
1'
b1 N
1J
1|
b10101 }
b1 ~
1Y
1.
1g
b0 ~
b110 $!
b110 #!
0q
1p
1o
08
17
16
0&
1%
1$
0Y
b101 $!
b101 #!
1q
0p
18
07
1&
0%
#120000
0!
0'
#130000
1!
1'
b10 N
0J
1I
0|
1{
b100001 }
b101 ~
b101 !!
1a
1_
1Y
1W
0.
0,
1+
00!
1/!
0g
0%!
0&!
1%!
b1 ~
b110 $!
b110 #!
0:
0q
1p
08
17
0&
1%
1g
0W
#140000
0!
0'
#150000
1!
1'
b11 N
1J
1|
b11110000 }
b110 ~
0Y
1X
1W
00
1,
1*
1)
10!
1.!
1-!
0%!
1,!
b110 !!
b1011 $!
b1011 #!
09
1?
1q
0o
1n
0a
1`
18
06
15
0%
0$
0i
1h
b1100 $!
b1100 #!
0q
0p
1o
08
07
16
